[{"u":"/","f":"$","i":"/"},{"u":"(","f":"^","i":"("},{"u":")","f":"&","i":")"},{"u":"+","f":"В¬","i":"+"},{"u":"%","f":"]","i":"%"},{"u":"'","f":"z","i":"'"},{"u":"!","f":"ГҰ","i":"!"},{"u":"\"","f":"Лң","i":"z"},{"u":",","f":"\"","i":","},{"u":":","f":"(","i":"Вә"},{"u":".","f":"'","i":"."},{"u":"вҖқ","f":"Лң","i":"z"},{"u":"вҖҷ","f":"Z","i":"'"},{"u":"а·Ға·ҠвҖҚа¶»а·’","f":"Y%s","i":"|ВұвҖ№"},{"u":"а·Ға·ҠвҖҚа¶»а·“","f":"вҖә","i":"|ВұЕЎ"},{"u":"а¶…","f":"w","i":"R"},{"u":"а¶Ҷ","f":"wd","i":"RВЈ"},{"u":"а¶Ү","f":"we","i":"RВҘ"},{"u":"а¶Ҳ","f":"wE","i":"RВҰ"},{"u":"а¶ү","f":"b","i":"S"},{"u":"а¶Ҡ","f":"B","i":"T"},{"u":"а¶Ӣ","f":"W","i":"U"},{"u":"а¶Ң","f":"W!","i":"UВ°"},{"u":"а¶Қ","f":"R","i":"V"},{"u":"а¶Һ","f":"RD","i":"а¶Һ"},{"u":"а¶Ҹ","f":"ГҢ","i":"а¶Ҹ"},{"u":"а¶җ","f":"ГҸ","i":"а¶җ"},{"u":"а¶‘","f":"t","i":"W"},{"u":"а¶’","f":"tA","i":"A"},{"u":"а¶“","f":"ft","i":"В»W"},{"u":"а¶”","f":"T","i":"X"},{"u":"а¶•","f":"Вҙ","i":"B"},{"u":"а¶–","f":"T!","i":"XВ°"},{"u":"а¶…а¶Ӯ","f":"wx","i":"RВ№"},{"u":"а¶…а¶ғ","f":"w#","i":"RВә"},{"u":"а¶ҡа·ҠвҖҚа¶әа·Ҹ","f":"lHd","i":"YВіВЈ"},{"u":"а¶ҡа·ҠвҖҚа¶әа·ң","f":"flHd","i":"В»YВіВЈ"},{"u":"а¶ҡа·ҠвҖҚа¶әа·қ","f":"flHda","i":"В»YВіВЈЕ "},{"u":"а¶ҡа·ҠвҖҚа¶»а·Ҹ","f":"l%d","i":"YВұВЈ"},{"u":"а¶ҡа·ҠвҖҚа¶»а·җ","f":"l%e","i":"YВұВҘ"},{"u":"а¶ҡа·ҠвҖҚа¶»а·‘","f":"l%E","i":"YВұВҰ"},{"u":"а¶ҡа·ҠвҖҚа¶»а·’","f":"l%s","i":"YВұвҖ№"},{"u":"а¶ҡа·ҠвҖҚа¶»а·“","f":"l%S","i":"YВұЕЎ"},{"u":"а¶ҡа·ҠвҖҚа¶»а·ҷ","f":"fl%","i":"В»YВұ"},{"u":"а¶ҡа·ҠвҖҚа¶»а·ҡ","f":"fl%a","i":"В»YЕ Вұ"},{"u":"а¶ҡа·ҠвҖҚа¶»а·ң","f":"fl%d","i":"В»YВұВЈ"},{"u":"а¶ҡа·ҠвҖҚа¶»а·қ","f":"fl%da","i":"В»YВұВЈЕ "},{"u":"а¶ҡа·ҠвҖҚа¶»а·ӣ","f":"ffl%","i":"YВұа·ӣ"},{"u":"а¶ҡа·ҠвҖҚа¶»а·һ","f":"fl%!","i":"YВұа·һ"},{"u":"а¶ҡа·ҠвҖҚа¶»а¶Ӯ","f":"l%x","i":"YВұВ№"},{"u":"а¶ҡа·ҠвҖҚа¶»а¶ғ","f":"l%#","i":"YВұВә"},{"u":"а¶ҡа·ҠвҖҚа¶ә","f":"lH","i":"YВі"},{"u":"а¶ҡа·ҠвҖҚа¶»","f":"l%","i":"YВұ"},{"u":"а¶ҡа·Ҡ","f":"la","i":"YЕ "},{"u":"а¶ҡа·Ҹ","f":"ld","i":"YВЈ"},{"u":"а¶ҡа·‘","f":"lE","i":"YВҰ"},{"u":"а¶ҡа·’","f":"ls","i":"YвҖ№"},{"u":"а¶ҡа·“","f":"lS","i":"YЕЎ"},{"u":"а¶ҡа·”","f":"l=","i":"YВӘ"},{"u":"а¶ҡа·–","f":"l+","i":"YВ®"},{"u":"а¶ҡа·ҳ","f":"lD","i":"YВҜ"},{"u":"а¶ҡа·І","f":"lDD","i":"YВҜВҜ"},{"u":"а¶ҡа·ҹ","f":"l!","i":"YВ°"},{"u":"а¶ҡа·і","f":"l!","i":"Yа·і"},{"u":"а¶ҡа·ҷ","f":"fl","i":"В»Y"},{"u":"а¶ҡа·ҡ","f":"fla","i":"В»YЕ "},{"u":"а¶ҡа·ӣ","f":"ffl","i":"В»В»Y"},{"u":"а¶ҡа·ң","f":"fld","i":"В»YВЈ"},{"u":"а¶ҡа·қ","f":"flda","i":"В»YВЈЕ "},{"u":"а¶ҡа·һ","f":"fl!","i":"В»YВ°"},{"u":"а¶ҡа¶Ӯ","f":"lx","i":"YВ№"},{"u":"а¶ҡа¶ғ","f":"l#","i":"YВә"},{"u":"а¶ҡ","f":"l","i":"Y"},{"u":"а¶ӣа·ҠвҖҚа¶әа·Ҹ","f":"LHd","i":"ZВіВЈ"},{"u":"а¶ӣа·ҠвҖҚа¶әа·ң","f":"fLHd","i":"В»ZВіВЈ"},{"u":"а¶ӣа·ҠвҖҚа¶әа·қ","f":"fLHda","i":"В»ZВіВЈЕ "},{"u":"а¶ӣа·ҠвҖҚа¶»а·Ҹ","f":"L%d","i":"ZВұВЈ"},{"u":"а¶ӣа·ҠвҖҚа¶»а·җ","f":"L%e","i":"ZВұВҘ"},{"u":"а¶ӣа·ҠвҖҚа¶»а·‘","f":"L%E","i":"ZВұВҰ"},{"u":"а¶ӣа·ҠвҖҚа¶»а·’","f":"Г…%","i":"ZВұвҖ№"},{"u":"а¶ӣа·ҠвҖҚа¶»а·“","f":"ГҮ%","i":"ZВұЕЎ"},{"u":"а¶ӣа·ҠвҖҚа¶»а·ҷ","f":"fL%","i":"ZВұВ»"},{"u":"а¶ӣа·ҠвҖҚа¶»а·ҡ","f":"fГ„%","i":"ZВұа·ҡ"},{"u":"а¶ӣа·ҠвҖҚа¶»а·ң","f":"fL%d","i":"ZВұа·ң"},{"u":"а¶ӣа·ҠвҖҚа¶»а·қ","f":"fL%da","i":"ZВұа·қ"},{"u":"а¶ӣа·ҠвҖҚа¶»а·ӣ","f":"ffL%","i":"ZВұа·ӣ"},{"u":"а¶ӣа·ҠвҖҚа¶»а·һ","f":"fL%!","i":"ZВұа·һ"},{"u":"а¶ӣа·ҠвҖҚа¶»а¶Ӯ","f":"L%x","i":"ZВұВ№"},{"u":"а¶ӣа·ҠвҖҚа¶»а¶ғ","f":"L%#","i":"ZВұВә"},{"u":"а¶ӣа·ҠвҖҚа¶ә","f":"LH","i":"ZВі"},{"u":"а¶ӣа·ҠвҖҚа¶»","f":"L%","i":"ZВұ"},{"u":"а¶ӣа·Ҡ","f":"Г„","i":"C"},{"u":"а¶ӣа·Ҹ","f":"Ld","i":"ZВЈ"},{"u":"а¶ӣа·‘","f":"LE","i":"ZВҰ"},{"u":"а¶ӣа·’","f":"Г…","i":"Г…"},{"u":"а¶ӣа·“","f":"ГҮ","i":"ГҶ"},{"u":"а¶ӣа·”","f":"Lq","i":"ZВ§"},{"u":"а¶ӣа·–","f":"LQ","i":"ZВ«"},{"u":"а¶ӣа·ҳ","f":"LD","i":"ZВҜ"},{"u":"а¶ӣа·І","f":"LDD","i":"ZВҜВҜ"},{"u":"а¶ӣа·ҹ","f":"L!","i":"ZВ°"},{"u":"а¶ӣа·і","f":"L!","i":"Zа·і"},{"u":"а¶ӣа·ҷ","f":"fL","i":"В»t"},{"u":"а¶ӣа·ҡ","f":"fГ„","i":"В»C"},{"u":"а¶ӣа·ӣ","f":"ffL","i":"Zа·ӣ"},{"u":"а¶ӣа·ң","f":"fLd","i":"В»ZВЈ"},{"u":"а¶ӣа·қ","f":"fLda","i":"В»ZВЈЕ "},{"u":"а¶ӣа·һ","f":"fL!","i":"Zа·һ"},{"u":"а¶ӣа¶Ӯ","f":"Lx","i":"ZВ№"},{"u":"а¶ӣа¶ғ","f":"L#","i":"ZВә"},{"u":"а¶ӣ","f":"L","i":"Z"},{"u":"а¶ңа·ҠвҖҚа¶әа·Ҹ","f":".Hd","i":"[ВіВЈ"},{"u":"а¶ңа·ҠвҖҚа¶әа·ң","f":"f.Hd","i":"В»[ВіВЈ"},{"u":"а¶ңа·ҠвҖҚа¶әа·қ","f":"f.Hda","i":"В»[ВіВЈЕ "},{"u":"а¶ңа·ҠвҖҚа¶»а·Ҹ","f":".%d","i":"[ВұВЈ"},{"u":"а¶ңа·ҠвҖҚа¶»а·җ","f":".%e","i":"[ВұВҘ"},{"u":"а¶ңа·ҠвҖҚа¶»а·‘","f":".%E","i":"[ВұВҰ"},{"u":"а¶ңа·ҠвҖҚа¶»а·’","f":".%s","i":"[ВұвҖ№"},{"u":"а¶ңа·ҠвҖҚа¶»а·“","f":".%S","i":"[ВұЕЎ"},{"u":"а¶ңа·ҠвҖҚа¶»а·ҷ","f":"f.%","i":"В»[Вұ"},{"u":"а¶ңа·ҠвҖҚа¶»а·ҡ","f":"f.%a","i":"В»[Е Вұ"},{"u":"а¶ңа·ҠвҖҚа¶»а·ң","f":"f.%d","i":"В»[ВұВЈ"},{"u":"а¶ңа·ҠвҖҚа¶»а·қ","f":"f.%da","i":"В»[ВұВЈЕ "},{"u":"а¶ңа·ҠвҖҚа¶»а·ӣ","f":"ff.%","i":"[Вұа·ӣ"},{"u":"а¶ңа·ҠвҖҚа¶»а·һ","f":"f.%!","i":"[Вұа·һ"},{"u":"а¶ңа·ҠвҖҚа¶»а¶Ӯ","f":".%x","i":"[ВұВ№"},{"u":"а¶ңа·ҠвҖҚа¶»а¶ғ","f":".%#","i":"[ВұВә"},{"u":"а¶ңа·ҠвҖҚа¶ә","f":".H","i":"[Ві"},{"u":"а¶ңа·ҠвҖҚа¶»","f":".%","i":"[Вұ"},{"u":"а¶ңа·Ҡ","f":".a","i":"[Е "},{"u":"а¶ңа·Ҹ","f":".d","i":"[ВЈ"},{"u":"а¶ңа·‘","f":".E","i":"[ВҰ"},{"u":"а¶ңа·’","f":".s","i":"[вҖ№"},{"u":"а¶ңа·“","f":".S","i":"[ЕЎ"},{"u":"а¶ңа·”","f":".=","i":"[ВӘ"},{"u":"а¶ңа·–","f":".+","i":"[В®"},{"u":"а¶ңа·ҳ","f":".D","i":"[ВҜ"},{"u":"а¶ңа·І","f":".DD","i":"[ВҜВҜ"},{"u":"а¶ңа·ҹ","f":".!","i":"[В°"},{"u":"а¶ңа·і","f":".!","i":"[а·і"},{"u":"а¶ңа·ҷ","f":"f.","i":"В»["},{"u":"а¶ңа·ҡ","f":"f.a","i":"В»[Е "},{"u":"а¶ңа·ӣ","f":"ff.","i":"[а·ӣ"},{"u":"а¶ңа·ң","f":"f.d","i":"В»[ВЈ"},{"u":"а¶ңа·қ","f":"f.da","i":"В»[ВЈЕ "},{"u":"а¶ңа·һ","f":"f.!","i":"В»[В°"},{"u":"а¶ңа¶Ӯ","f":".x","i":"[В№"},{"u":"а¶ңа¶ғ","f":".#","i":"[Вә"},{"u":"а¶ң","f":".","i":"["},{"u":"а¶қа·ҠвҖҚа¶әа·Ҹ","f":">Hd","i":"]ВіВЈ"},{"u":"а¶қа·ҠвҖҚа¶әа·ң","f":"f>Hd","i":"]Віа·ң"},{"u":"а¶қа·ҠвҖҚа¶әа·қ","f":"f>Hda","i":"В»]ВіВЈЕ "},{"u":"а¶қа·ҠвҖҚа¶»а·Ҹ","f":">%d","i":"]ВұВЈ"},{"u":"а¶қа·ҠвҖҚа¶»а·җ","f":">%e","i":"]ВұВҘ"},{"u":"а¶қа·ҠвҖҚа¶»а·‘","f":">%E","i":"]ВұВҰ"},{"u":"а¶қа·ҠвҖҚа¶»а·’","f":">%s","i":"]ВұвҖ№"},{"u":"а¶қа·ҠвҖҚа¶»а·“","f":">%S","i":"]ВұЕЎ"},{"u":"а¶қа·ҠвҖҚа¶»а·ҷ","f":"f>%","i":"]ВұВ»"},{"u":"а¶қа·ҠвҖҚа¶»а·ҡ","f":"f>%a","i":"]Вұа·ҡ"},{"u":"а¶қа·ҠвҖҚа¶»а·ң","f":"f>%d","i":"]Вұа·ң"},{"u":"а¶қа·ҠвҖҚа¶»а·қ","f":"f>%da","i":"В»]ВұВЈЕ "},{"u":"а¶қа·ҠвҖҚа¶»а·ӣ","f":"ff>%","i":"]Вұа·ӣ"},{"u":"а¶қа·ҠвҖҚа¶»а·һ","f":"f>%!","i":"]Вұа·һ"},{"u":"а¶қа·ҠвҖҚа¶»а¶Ӯ","f":">%x","i":"]ВұВ№"},{"u":"а¶қа·ҠвҖҚа¶»а¶ғ","f":">%#","i":"]ВұВә"},{"u":"а¶қа·ҠвҖҚа¶ә","f":">H","i":"]Ві"},{"u":"а¶қа·ҠвҖҚа¶»","f":">%","i":"]Вұ"},{"u":"а¶қа·Ҡ","f":">a","i":"]Е "},{"u":"а¶қа·Ҹ","f":">d","i":"]ВЈ"},{"u":"а¶қа·‘","f":">E","i":"]ВҰ"},{"u":"а¶қа·’","f":">s","i":"]вҖ№"},{"u":"а¶қа·“","f":">S","i":"]ЕЎ"},{"u":"а¶қа·”","f":">q","i":"]В§"},{"u":"а¶қа·–","f":">Q","i":"]В«"},{"u":"а¶қа·ҳ","f":">D","i":"]ВҜ"},{"u":"а¶қа·І","f":">DD","i":"]ВҜВҜ"},{"u":"а¶қа·ҹ","f":">!","i":"]В°"},{"u":"а¶қа·і","f":">!","i":"]а·і"},{"u":"а¶қа·ҷ","f":"f>","i":"В»]"},{"u":"а¶қа·ҡ","f":"f>a","i":"В»]Е "},{"u":"а¶қа·ӣ","f":"ff>","i":"]а·ӣ"},{"u":"а¶қа·ң","f":"f>d","i":"В»]ВЈ"},{"u":"а¶қа·қ","f":"f>da","i":"В»]ВЈЕ "},{"u":"а¶қа·һ","f":"f>!","i":"]а·һ"},{"u":"а¶қа¶Ӯ","f":">x","i":"]В№"},{"u":"а¶қа¶ғ","f":">#","i":"]Вә"},{"u":"а¶қ","f":">","i":"]"},{"u":"а¶һа·ҠвҖҚа¶әа·Ҹ","f":"ГҷHd","i":"а¶һВіВЈ"},{"u":"а¶һа·ҠвҖҚа¶әа·ң","f":"fГҷHd","i":"а¶һВіа·ң"},{"u":"а¶һа·ҠвҖҚа¶әа·қ","f":"fГҷHda","i":"а¶һВіа·қ"},{"u":"а¶һа·ҠвҖҚа¶»а·Ҹ","f":"Гҷ%d","i":"а¶һВұВЈ"},{"u":"а¶һа·ҠвҖҚа¶»а·җ","f":"Гҷ%e","i":"а¶һВұВҘ"},{"u":"а¶һа·ҠвҖҚа¶»а·‘","f":"Гҷ%E","i":"а¶һВұВҰ"},{"u":"а¶һа·ҠвҖҚа¶»а·’","f":"Гҷ%s","i":"а¶һВұвҖ№"},{"u":"а¶һа·ҠвҖҚа¶»а·“","f":"Гҷ%S","i":"а¶һВұЕЎ"},{"u":"а¶һа·ҠвҖҚа¶»а·ҷ","f":"fГҷ%","i":"а¶һВұВ»"},{"u":"а¶һа·ҠвҖҚа¶»а·ҡ","f":"fГҷ%a","i":"а¶һВұа·ҡ"},{"u":"а¶һа·ҠвҖҚа¶»а·ң","f":"fГҷ%d","i":"а¶һВұа·ң"},{"u":"а¶һа·ҠвҖҚа¶»а·қ","f":"fГҷ%da","i":"а¶һВұа·қ"},{"u":"а¶һа·ҠвҖҚа¶»а·ӣ","f":"ffГҷ%","i":"а¶һВұа·ӣ"},{"u":"а¶һа·ҠвҖҚа¶»а·һ","f":"fГҷ%!","i":"а¶һВұа·һ"},{"u":"а¶һа·ҠвҖҚа¶»а¶Ӯ","f":"Гҷ%x","i":"а¶һВұВ№"},{"u":"а¶һа·ҠвҖҚа¶»а¶ғ","f":"Гҷ%#","i":"а¶һВұВә"},{"u":"а¶һа·ҠвҖҚа¶ә","f":"ГҷH","i":"а¶һВі"},{"u":"а¶һа·ҠвҖҚа¶»","f":"Гҷ%","i":"а¶һВұ"},{"u":"а¶һа·Ҹ","f":"Гҷd","i":"а¶һВЈ"},{"u":"а¶һа·‘","f":"ГҷE","i":"а¶һВҰ"},{"u":"а¶һа·’","f":"Гҷs","i":"а¶һвҖ№"},{"u":"а¶һа·“","f":"ГҷS","i":"а¶һЕЎ"},{"u":"а¶һа·”","f":"Гҷq","i":"а¶һВ§"},{"u":"а¶һа·–","f":"ГҷQ","i":"а¶һВ«"},{"u":"а¶һа·ҳ","f":"ГҷD","i":"а¶һВҜ"},{"u":"а¶һа·І","f":"ГҷDD","i":"а¶һВҜВҜ"},{"u":"а¶һа·ҹ","f":"Гҷ!","i":"а¶һВ°"},{"u":"а¶һа·і","f":"Гҷ!","i":"а¶һа·і"},{"u":"а¶һа·ҷ","f":"fГҷ","i":"а¶һВ»"},{"u":"а¶һа·ҡ","f":"fГҷa","i":"а¶һа·ҡ"},{"u":"а¶һа·ӣ","f":"ffГҷ","i":"а¶һа·ӣ"},{"u":"а¶һа·ң","f":"fГҷd","i":"а¶һа·ң"},{"u":"а¶һа·қ","f":"fГҷda","i":"а¶һа·қ"},{"u":"а¶һа·һ","f":"fГҷ!","i":"а¶һа·һ"},{"u":"а¶һа¶Ӯ","f":"Гҷx","i":"а¶һВ№"},{"u":"а¶һа¶ғ","f":"Гҷ#","i":"а¶һВә"},{"u":"а¶һ","f":"Гҷ","i":"а¶һ"},{"u":"а¶ҹа·ҠвҖҚа¶әа·Ҹ","f":"Г•Hd","i":"`ВіВЈ"},{"u":"а¶ҹа·ҠвҖҚа¶әа·ң","f":"fГ•Hd","i":"`Віа·ң"},{"u":"а¶ҹа·ҠвҖҚа¶әа·қ","f":"fГ•Hda","i":"`Віа·қ"},{"u":"а¶ҹа·ҠвҖҚа¶»а·Ҹ","f":"Г•%d","i":"`ВұВЈ"},{"u":"а¶ҹа·ҠвҖҚа¶»а·җ","f":"Г•%e","i":"`ВұВҘ"},{"u":"а¶ҹа·ҠвҖҚа¶»а·‘","f":"Г•%E","i":"`ВұВҰ"},{"u":"а¶ҹа·ҠвҖҚа¶»а·’","f":"Г•%s","i":"`ВұвҖ№"},{"u":"а¶ҹа·ҠвҖҚа¶»а·“","f":"Г•%S","i":"`ВұЕЎ"},{"u":"а¶ҹа·ҠвҖҚа¶»а·ҷ","f":"fГ•%","i":"`ВұВ»"},{"u":"а¶ҹа·ҠвҖҚа¶»а·ҡ","f":"fГ•%a","i":"`Вұа·ҡ"},{"u":"а¶ҹа·ҠвҖҚа¶»а·ң","f":"fГ•%d","i":"`Вұа·ң"},{"u":"а¶ҹа·ҠвҖҚа¶»а·қ","f":"fГ•%da","i":"`Вұа·қ"},{"u":"а¶ҹа·ҠвҖҚа¶»а·ӣ","f":"ffГ•%","i":"`Вұа·ӣ"},{"u":"а¶ҹа·ҠвҖҚа¶»а·һ","f":"fГ•%!","i":"`Вұа·һ"},{"u":"а¶ҹа·ҠвҖҚа¶»а¶Ӯ","f":"Г•%x","i":"`ВұВ№"},{"u":"а¶ҹа·ҠвҖҚа¶»а¶ғ","f":"Г•%#","i":"`ВұВә"},{"u":"а¶ҹа·ҠвҖҚа¶ә","f":"Г•H","i":"`Ві"},{"u":"а¶ҹа·ҠвҖҚа¶»","f":"Г•%","i":"`Вұ"},{"u":"а¶ҹа·Ҡ","f":"Г•a","i":"`Е "},{"u":"а¶ҹа·Ҹ","f":"Г•d","i":"`ВЈ"},{"u":"а¶ҹа·‘","f":"Г•E","i":"`ВҰ"},{"u":"а¶ҹа·’","f":"Г•s","i":"`вҖ№"},{"u":"а¶ҹа·“","f":"Г•S","i":"`ЕЎ"},{"u":"а¶ҹа·”","f":"Г•=","i":"`В§"},{"u":"а¶ҹа·–","f":"Г•+","i":"`В«"},{"u":"а¶ҹа·ҳ","f":"Г•D","i":"`ВҜ"},{"u":"а¶ҹа·І","f":"Г•DD","i":"`ВҜВҜ"},{"u":"а¶ҹа·ҹ","f":"Г•!","i":"`В°"},{"u":"а¶ҹа·і","f":"Г•!","i":"`а·і"},{"u":"а¶ҹа·ҷ","f":"fГ•","i":"В»"},{"u":"а¶ҹа·ҡ","f":"fГ•a","i":"В»Е "},{"u":"а¶ҹа·ӣ","f":"ffГ•","i":"`а·ӣ"},{"u":"а¶ҹа·ң","f":"fГ•d","i":"В»ВЈ"},{"u":"а¶ҹа·қ","f":"fГ•da","i":"В»ВЈЕ "},{"u":"а¶ҹа·һ","f":"fГ•!","i":"`а·һ"},{"u":"а¶ҹа¶Ӯ","f":"Г•x","i":"`В№"},{"u":"а¶ҹа¶ғ","f":"Г•#","i":"`Вә"},{"u":"а¶ҹ","f":"Г•","i":"`"},{"u":"а¶ а·ҠвҖҚа¶әа·Ҹ","f":"pHd","i":"aВіВЈ"},{"u":"а¶ а·ҠвҖҚа¶әа·ң","f":"fpHd","i":"aВіа·ң"},{"u":"а¶ а·ҠвҖҚа¶әа·қ","f":"fpHda","i":"В»aВіВЈЕ "},{"u":"а¶ а·ҠвҖҚа¶»а·Ҹ","f":"p%d","i":"aВұВЈ"},{"u":"а¶ а·ҠвҖҚа¶»а·җ","f":"p%e","i":"aВұВҘ"},{"u":"а¶ а·ҠвҖҚа¶»а·‘","f":"p%E","i":"aВұВҰ"},{"u":"а¶ а·ҠвҖҚа¶»а·’","f":"Г‘%","i":"aВұвҖ№"},{"u":"а¶ а·ҠвҖҚа¶»а·“","f":"Г–%","i":"aВұЕЎ"},{"u":"а¶ а·ҠвҖҚа¶»а·ҷ","f":"fp%","i":"aВұВ»"},{"u":"а¶ а·ҠвҖҚа¶»а·ҡ","f":"fГү%","i":"aВұа·ҡ"},{"u":"а¶ а·ҠвҖҚа¶»а·ң","f":"fp%d","i":"aВұа·ң"},{"u":"а¶ а·ҠвҖҚа¶»а·қ","f":"fp%da","i":"aВұа·қ"},{"u":"а¶ а·ҠвҖҚа¶»а·ӣ","f":"ffp%","i":"aВұа·ӣ"},{"u":"а¶ а·ҠвҖҚа¶»а·һ","f":"fp%!","i":"aВұа·һ"},{"u":"а¶ а·ҠвҖҚа¶»а¶Ӯ","f":"p%x","i":"aВұВ№"},{"u":"а¶ а·ҠвҖҚа¶»а¶ғ","f":"p%#","i":"aВұВә"},{"u":"а¶ а·ҠвҖҚа¶ә","f":"pH","i":"aВі"},{"u":"а¶ а·ҠвҖҚа¶»","f":"p%","i":"aВұ"},{"u":"а¶ а·Ҡ","f":"Гү","i":"D"},{"u":"а¶ а·Ҹ","f":"pd","i":"aВЈ"},{"u":"а¶ а·‘","f":"pE","i":"aВҰ"},{"u":"а¶ а·’","f":"Г‘","i":"ГҮ"},{"u":"а¶ а·“","f":"Г–","i":"ГҲ"},{"u":"а¶ а·”","f":"pq","i":"aВ§"},{"u":"а¶ а·–","f":"pQ","i":"aВ«"},{"u":"а¶ а·ҳ","f":"pD","i":"aВҜ"},{"u":"а¶ а·І","f":"pDD","i":"aВҜВҜ"},{"u":"а¶ а·ҹ","f":"p!","i":"aВ°"},{"u":"а¶ а·і","f":"p!","i":"aа·і"},{"u":"а¶ а·ҷ","f":"fp","i":"В»a"},{"u":"а¶ а·ҡ","f":"fГү","i":"В»D"},{"u":"а¶ а·ӣ","f":"ffp","i":"В»В»a"},{"u":"а¶ а·ң","f":"fpd","i":"В»aВЈ"},{"u":"а¶ а·қ","f":"fpda","i":"В»aВЈЕ "},{"u":"а¶ а·һ","f":"fp!","i":"В»aВ°"},{"u":"а¶ а¶Ӯ","f":"px","i":"aВ№"},{"u":"а¶ а¶ғ","f":"p#","i":"aВә"},{"u":"а¶ ","f":"p","i":"a"},{"u":"а¶Ўа·ҠвҖҚа¶әа·Ҹ","f":"PHd","i":"bВіВЈ"},{"u":"а¶Ўа·ҠвҖҚа¶әа·ң","f":"fPHd","i":"bВіа·ң"},{"u":"а¶Ўа·ҠвҖҚа¶әа·қ","f":"fPHda","i":"В»bВіВЈЕ "},{"u":"а¶Ўа·ҠвҖҚа¶»а·Ҹ","f":"P%d","i":"bВұВЈ"},{"u":"а¶Ўа·ҠвҖҚа¶»а·җ","f":"P%e","i":"bВұВҘ"},{"u":"а¶Ўа·ҠвҖҚа¶»а·‘","f":"P%E","i":"bВұВҰ"},{"u":"а¶Ўа·ҠвҖҚа¶»а·’","f":"P%s","i":"bВұвҖ№"},{"u":"а¶Ўа·ҠвҖҚа¶»а·“","f":"P%S","i":"bВұЕЎ"},{"u":"а¶Ўа·ҠвҖҚа¶»а·ҷ","f":"fP%","i":"bВұВ»"},{"u":"а¶Ўа·ҠвҖҚа¶»а·ҡ","f":"fP%a","i":"bВұа·ҡ"},{"u":"а¶Ўа·ҠвҖҚа¶»а·ң","f":"fP%d","i":"bВұа·ң"},{"u":"а¶Ўа·ҠвҖҚа¶»а·қ","f":"fP%da","i":"bВұа·қ"},{"u":"а¶Ўа·ҠвҖҚа¶»а·ӣ","f":"ffP%","i":"bВұа·ӣ"},{"u":"а¶Ўа·ҠвҖҚа¶»а·һ","f":"fP%!","i":"bВұа·һ"},{"u":"а¶Ўа·ҠвҖҚа¶»а¶Ӯ","f":"P%x","i":"bВұВ№"},{"u":"а¶Ўа·ҠвҖҚа¶»а¶ғ","f":"P%#","i":"bВұВә"},{"u":"а¶Ўа·ҠвҖҚа¶ә","f":"PH","i":"bВі"},{"u":"а¶Ўа·ҠвҖҚа¶»","f":"P%","i":"bВұ"},{"u":"а¶Ўа·Ҡ","f":"Гҫ","i":"E"},{"u":"а¶Ўа·Ҹ","f":"Pd","i":"bВЈ"},{"u":"а¶Ўа·‘","f":"PE","i":"bВҰ"},{"u":"а¶Ўа·’","f":"ГҪ","i":"Гү"},{"u":"а¶Ўа·“","f":"ГӮ","i":"Гү"},{"u":"а¶Ўа·”","f":"Pq","i":"bВ§"},{"u":"а¶Ўа·–","f":"PQ","i":"bВ«"},{"u":"а¶Ўа·ҳ","f":"PD","i":"bВҜ"},{"u":"а¶Ўа·І","f":"PDD","i":"bВҜВҜ"},{"u":"а¶Ўа·ҹ","f":"P!","i":"bВ°"},{"u":"а¶Ўа·і","f":"P!","i":"bа·і"},{"u":"а¶Ўа·ҷ","f":"fP","i":"В»b"},{"u":"а¶Ўа·ҡ","f":"fГҫ","i":"В»E"},{"u":"а¶Ўа·ӣ","f":"ffP","i":"bа·ӣ"},{"u":"а¶Ўа·ң","f":"fPd","i":"В»bВЈ"},{"u":"а¶Ўа·қ","f":"fPda","i":"В»bВЈЕ "},{"u":"а¶Ўа·һ","f":"fP!","i":"В»bВ°"},{"u":"а¶Ўа¶Ӯ","f":"Px","i":"bВ№"},{"u":"а¶Ўа¶ғ","f":"P#","i":"bВә"},{"u":"а¶Ў","f":"P","i":"b"},{"u":"а¶ўа·ҠвҖҚа¶әа·Ҹ","f":"cHd","i":"cВіВЈ"},{"u":"а¶ўа·ҠвҖҚа¶әа·ң","f":"fcHd","i":"В»cВіВЈ"},{"u":"а¶ўа·ҠвҖҚа¶әа·қ","f":"fcHda","i":"В»cВіВЈЕ "},{"u":"а¶ўа·ҠвҖҚа¶»а·Ҹ","f":"c%d","i":"cВұВЈ"},{"u":"а¶ўа·ҠвҖҚа¶»а·җ","f":"c%e","i":"cВұВҘ"},{"u":"а¶ўа·ҠвҖҚа¶»а·‘","f":"c%E","i":"cВұВҰ"},{"u":"а¶ўа·ҠвҖҚа¶»а·’","f":"c%s","i":"cВұвҖ№"},{"u":"а¶ўа·ҠвҖҚа¶»а·“","f":"c%S","i":"cВұЕЎ"},{"u":"а¶ўа·ҠвҖҚа¶»а·ҷ","f":"fc%","i":"cВұВ»"},{"u":"а¶ўа·ҠвҖҚа¶»а·ҡ","f":"fc%a","i":"cВұа·ҡ"},{"u":"а¶ўа·ҠвҖҚа¶»а·ң","f":"fc%d","i":"cВұа·ң"},{"u":"а¶ўа·ҠвҖҚа¶»а·қ","f":"fc%da","i":"cВұа·қ"},{"u":"а¶ўа·ҠвҖҚа¶»а·ӣ","f":"ffc%","i":"cВұа·ӣ"},{"u":"а¶ўа·ҠвҖҚа¶»а·һ","f":"fc%!","i":"cВұа·һ"},{"u":"а¶ўа·ҠвҖҚа¶»а¶Ӯ","f":"c%x","i":"cВұВ№"},{"u":"а¶ўа·ҠвҖҚа¶»а¶ғ","f":"c%#","i":"cВұВә"},{"u":"а¶ўа·ҠвҖҚа¶ә","f":"cH","i":"cВі"},{"u":"а¶ўа·ҠвҖҚа¶»","f":"c%","i":"cВұ"},{"u":"а¶ўа·Ҡ","f":"ГҠ","i":"F"},{"u":"а¶ўа·Ҹ","f":"cd","i":"cВЈ"},{"u":"а¶ўа·‘","f":"cE","i":"cВҰ"},{"u":"а¶ўа·’","f":"Г°","i":"ГӢ"},{"u":"а¶ўа·“","f":"Г”","i":"ГҢ"},{"u":"а¶ўа·”","f":"cq","i":"cВ§"},{"u":"а¶ўа·–","f":"cQ","i":"cВ«"},{"u":"а¶ўа·ҳ","f":"cD","i":"cВҜ"},{"u":"а¶ўа·І","f":"cDD","i":"cВҜВҜ"},{"u":"а¶ўа·ҹ","f":"c!","i":"cВ°"},{"u":"а¶ўа·і","f":"c!","i":"cа·і"},{"u":"а¶ўа·ҷ","f":"fc","i":"В»c"},{"u":"а¶ўа·ҡ","f":"fГҠ","i":"В»cвҖ°"},{"u":"а¶ўа·ӣ","f":"ffc","i":"В»В»c"},{"u":"а¶ўа·ң","f":"fcd","i":"В»cВЈ"},{"u":"а¶ўа·қ","f":"fcda","i":"В»cВЈЕ "},{"u":"а¶ўа·һ","f":"fc!","i":"В»cВ°"},{"u":"а¶ўа¶Ӯ","f":"cx","i":"cВ№"},{"u":"а¶ўа¶ғ","f":"c#","i":"cВә"},{"u":"а¶ў","f":"c","i":"c"},{"u":"а¶Ја·ҠвҖҚа¶әа·Ҹ","f":"В®Hd","i":"вҖһВіВЈ"},{"u":"а¶Ја·ҠвҖҚа¶әа·ң","f":"fВ®Hd","i":"вҖһВіа·ң"},{"u":"а¶Ја·ҠвҖҚа¶әа·қ","f":"fВ®Hda","i":"вҖһВіа·қ"},{"u":"а¶Ја·ҠвҖҚа¶»а·Ҹ","f":"В®%d","i":"вҖһВұВЈ"},{"u":"а¶Ја·ҠвҖҚа¶»а·җ","f":"В®%e","i":"вҖһВұВҘ"},{"u":"а¶Ја·ҠвҖҚа¶»а·‘","f":"В®%E","i":"вҖһВұВҰ"},{"u":"а¶Ја·ҠвҖҚа¶»а·’","f":"В®%s","i":"вҖһВұвҖ№"},{"u":"а¶Ја·ҠвҖҚа¶»а·“","f":"В®%S","i":"вҖһВұЕЎ"},{"u":"а¶Ја·ҠвҖҚа¶»а·ҷ","f":"fВ®%","i":"вҖһВұВ»"},{"u":"а¶Ја·ҠвҖҚа¶»а·ҡ","f":"fВ®%a","i":"вҖһВұа·ҡ"},{"u":"а¶Ја·ҠвҖҚа¶»а·ң","f":"fВ®%d","i":"вҖһВұа·ң"},{"u":"а¶Ја·ҠвҖҚа¶»а·қ","f":"fВ®%da","i":"вҖһВұа·қ"},{"u":"а¶Ја·ҠвҖҚа¶»а·ӣ","f":"ffВ®%","i":"вҖһВұа·ӣ"},{"u":"а¶Ја·ҠвҖҚа¶»а·һ","f":"fВ®%!","i":"вҖһВұа·һ"},{"u":"а¶Ја·ҠвҖҚа¶»а¶Ӯ","f":"В®%x","i":"вҖһВұВ№"},{"u":"а¶Ја·ҠвҖҚа¶»а¶ғ","f":"В®%#","i":"вҖһВұВә"},{"u":"а¶Ја·ҠвҖҚа¶ә","f":"В®H","i":"вҖһВі"},{"u":"а¶Ја·ҠвҖҚа¶»","f":"В®%","i":"вҖһВұ"},{"u":"а¶Ја·Ҡ","f":"В®a","i":"вҖһЕ "},{"u":"а¶Ја·Ҹ","f":"В®d","i":"вҖһВЈ"},{"u":"а¶Ја·‘","f":"В®E","i":"вҖһВҰ"},{"u":"а¶Ја·’","f":"В®s","i":"вҖһвҖ№"},{"u":"а¶Ја·“","f":"В®S","i":"вҖһЕЎ"},{"u":"а¶Ја·”","f":"В®q","i":"вҖһВ§"},{"u":"а¶Ја·–","f":"В®Q","i":"вҖһВ«"},{"u":"а¶Ја·ҳ","f":"В®D","i":"вҖһВҜ"},{"u":"а¶Ја·І","f":"В®DD","i":"вҖһВҜВҜ"},{"u":"а¶Ја·ҹ","f":"В®!","i":"вҖһВ°"},{"u":"а¶Ја·і","f":"В®!","i":"вҖһа·і"},{"u":"а¶Ја·ҷ","f":"fВ®","i":"вҖһВ»"},{"u":"а¶Ја·ҡ","f":"fВ®a","i":"вҖһа·ҡ"},{"u":"а¶Ја·ӣ","f":"ffВ®","i":"вҖһа·ӣ"},{"u":"а¶Ја·ң","f":"fВ®d","i":"вҖһа·ң"},{"u":"а¶Ја·қ","f":"fВ®da","i":"вҖһа·қ"},{"u":"а¶Ја·һ","f":"fВ®!","i":"вҖһа·һ"},{"u":"а¶Ја¶Ӯ","f":"В®x","i":"вҖһВ№"},{"u":"а¶Ја¶ғ","f":"В®#","i":"вҖһВә"},{"u":"а¶Ј","f":"В®","i":"вҖһ"},{"u":"а¶Өа·ҠвҖҚа¶әа·Ҹ","f":"[Hd","i":"dВіВЈ"},{"u":"а¶Өа·ҠвҖҚа¶әа·ң","f":"f[Hd","i":"dВіа·ң"},{"u":"а¶Өа·ҠвҖҚа¶әа·қ","f":"f[Hda","i":"dВіа·қ"},{"u":"а¶Өа·ҠвҖҚа¶»а·Ҹ","f":"[%d","i":"dВұВЈ"},{"u":"а¶Өа·ҠвҖҚа¶»а·җ","f":"[%e","i":"dВұВҘ"},{"u":"а¶Өа·ҠвҖҚа¶»а·‘","f":"[%E","i":"dВұВҰ"},{"u":"а¶Өа·ҠвҖҚа¶»а·’","f":"[%s","i":"dВұвҖ№"},{"u":"а¶Өа·ҠвҖҚа¶»а·“","f":"[%S","i":"dВұЕЎ"},{"u":"а¶Өа·ҠвҖҚа¶»а·ҷ","f":"f[%","i":"dВұВ»"},{"u":"а¶Өа·ҠвҖҚа¶»а·ҡ","f":"f[%a","i":"dВұа·ҡ"},{"u":"а¶Өа·ҠвҖҚа¶»а·ң","f":"f[%d","i":"dВұа·ң"},{"u":"а¶Өа·ҠвҖҚа¶»а·қ","f":"f[%da","i":"dВұа·қ"},{"u":"а¶Өа·ҠвҖҚа¶»а·ӣ","f":"ff[%","i":"dВұа·ӣ"},{"u":"а¶Өа·ҠвҖҚа¶»а·һ","f":"f[%!","i":"dВұа·һ"},{"u":"а¶Өа·ҠвҖҚа¶»а¶Ӯ","f":"[%x","i":"dВұВ№"},{"u":"а¶Өа·ҠвҖҚа¶»а¶ғ","f":"[%#","i":"dВұВә"},{"u":"а¶Өа·ҠвҖҚа¶ә","f":"[H","i":"dВі"},{"u":"а¶Өа·ҠвҖҚа¶»","f":"[%","i":"dВұ"},{"u":"а¶Өа·Ҡ","f":"[a","i":"dЕ "},{"u":"а¶Өа·Ҹ","f":"[d","i":"dВЈ"},{"u":"а¶Өа·‘","f":"[E","i":"dВҰ"},{"u":"а¶Өа·’","f":"[s","i":"dвҖ№"},{"u":"а¶Өа·“","f":"[S","i":"dЕЎ"},{"u":"а¶Өа·”","f":"Г»","i":"ГҺ"},{"u":"а¶Өа·–","f":"[Q","i":"dВ«"},{"u":"а¶Өа·ҳ","f":"[D","i":"dВҜ"},{"u":"а¶Өа·І","f":"[DD","i":"dВҜВҜ"},{"u":"а¶Өа·ҹ","f":"[!","i":"dВ°"},{"u":"а¶Өа·і","f":"[!","i":"dа·і"},{"u":"а¶Өа·ҷ","f":"f[","i":"В»d"},{"u":"а¶Өа·ҡ","f":"f[a","i":"В»dЕ "},{"u":"а¶Өа·ӣ","f":"ff[","i":"dа·ӣ"},{"u":"а¶Өа·ң","f":"f[d","i":"В»ГҚ"},{"u":"а¶Өа·қ","f":"f[da","i":"В»ГҚЕ "},{"u":"а¶Өа·һ","f":"f[!","i":"В»dВ°"},{"u":"а¶Өа¶Ӯ","f":"[x","i":"dВ№"},{"u":"а¶Өа¶ғ","f":"[#","i":"dВә"},{"u":"а¶Ө","f":"[","i":"d"},{"u":"а¶Ұа·ҠвҖҚа¶әа·Ҹ","f":"`cHd","i":"а¶ҰВіВЈ"},{"u":"а¶Ұа·ҠвҖҚа¶әа·ң","f":"f`cHd","i":"а¶ҰВіа·ң"},{"u":"а¶Ұа·ҠвҖҚа¶әа·қ","f":"f`cHda","i":"а¶ҰВіа·қ"},{"u":"а¶Ұа·ҠвҖҚа¶»а·Ҹ","f":"`c%d","i":"а¶ҰВұВЈ"},{"u":"а¶Ұа·ҠвҖҚа¶»а·җ","f":"`c%e","i":"а¶ҰВұВҘ"},{"u":"а¶Ұа·ҠвҖҚа¶»а·‘","f":"`c%E","i":"а¶ҰВұВҰ"},{"u":"а¶Ұа·ҠвҖҚа¶»а·’","f":"`c%s","i":"а¶ҰВұвҖ№"},{"u":"а¶Ұа·ҠвҖҚа¶»а·“","f":"`c%S","i":"а¶ҰВұЕЎ"},{"u":"а¶Ұа·ҠвҖҚа¶»а·ҷ","f":"f`c%","i":"а¶ҰВұВ»"},{"u":"а¶Ұа·ҠвҖҚа¶»а·ҡ","f":"f`c%a","i":"а¶ҰВұа·ҡ"},{"u":"а¶Ұа·ҠвҖҚа¶»а·ң","f":"f`c%d","i":"а¶ҰВұа·ң"},{"u":"а¶Ұа·ҠвҖҚа¶»а·қ","f":"f`c%da","i":"а¶ҰВұа·қ"},{"u":"а¶Ұа·ҠвҖҚа¶»а·ӣ","f":"ff`c%","i":"а¶ҰВұа·ӣ"},{"u":"а¶Ұа·ҠвҖҚа¶»а·һ","f":"f`c%!","i":"а¶ҰВұа·һ"},{"u":"а¶Ұа·ҠвҖҚа¶»а¶Ӯ","f":"`c%x","i":"а¶ҰВұВ№"},{"u":"а¶Ұа·ҠвҖҚа¶»а¶ғ","f":"`c%#","i":"а¶ҰВұВә"},{"u":"а¶Ұа·ҠвҖҚа¶ә","f":"`cH","i":"а¶ҰВі"},{"u":"а¶Ұа·ҠвҖҚа¶»","f":"`c%","i":"а¶ҰВұ"},{"u":"а¶Ұа·Ҡ","f":"`ca","i":"а¶ҰЕ "},{"u":"а¶Ұа·Ҹ","f":"`cd","i":"а¶ҰВЈ"},{"u":"а¶Ұа·‘","f":"`cE","i":"а¶ҰВҰ"},{"u":"а¶Ұа·’","f":"`cs","i":"а¶ҰвҖ№"},{"u":"а¶Ұа·“","f":"`cS","i":"а¶ҰЕЎ"},{"u":"а¶Ұа·”","f":"`cq","i":"а¶ҰВ§"},{"u":"а¶Ұа·–","f":"`cQ","i":"а¶ҰВ«"},{"u":"а¶Ұа·ҳ","f":"`cD","i":"а¶ҰВҜ"},{"u":"а¶Ұа·І","f":"`cDD","i":"а¶ҰВҜВҜ"},{"u":"а¶Ұа·ҹ","f":"`c!","i":"а¶ҰВ°"},{"u":"а¶Ұа·і","f":"`c!","i":"а¶Ұа·і"},{"u":"а¶Ұа·ҷ","f":"f`c","i":"а¶ҰВ»"},{"u":"а¶Ұа·ҡ","f":"f`ca","i":"а¶Ұа·ҡ"},{"u":"а¶Ұа·ӣ","f":"ff`c","i":"а¶Ұа·ӣ"},{"u":"а¶Ұа·ң","f":"f`cd","i":"а¶Ұа·ң"},{"u":"а¶Ұа·қ","f":"f`cda","i":"а¶Ұа·қ"},{"u":"а¶Ұа·һ","f":"f`c!","i":"а¶Ұа·һ"},{"u":"а¶Ұа¶Ӯ","f":"`cx","i":"а¶ҰВ№"},{"u":"а¶Ұа¶ғ","f":"`c#","i":"а¶ҰВә"},{"u":"а¶Ұ","f":"`c","i":"а¶Ұ"},{"u":"а¶§а·ҠвҖҚа¶әа·Ҹ","f":"gHd","i":"fВіВЈ"},{"u":"а¶§а·ҠвҖҚа¶әа·ң","f":"fgHd","i":"В»fВіВЈ"},{"u":"а¶§а·ҠвҖҚа¶әа·қ","f":"fgHda","i":"В»fВіВЈЕ "},{"u":"а¶§а·ҠвҖҚа¶»а·Ҹ","f":"g%d","i":"fВұВЈ"},{"u":"а¶§а·ҠвҖҚа¶»а·җ","f":"g%e","i":"fВұВҘ"},{"u":"а¶§а·ҠвҖҚа¶»а·‘","f":"g%E","i":"fВұВҰ"},{"u":"а¶§а·ҠвҖҚа¶»а·’","f":"ГЎ%","i":"fВұвҖ№"},{"u":"а¶§а·ҠвҖҚа¶»а·“","f":"Г %","i":"fВұЕЎ"},{"u":"а¶§а·ҠвҖҚа¶»а·ҷ","f":"fg%","i":"fВұВ»"},{"u":"а¶§а·ҠвҖҚа¶»а·ҡ","f":"fГң%","i":"fВұа·ҡ"},{"u":"а¶§а·ҠвҖҚа¶»а·ң","f":"fg%d","i":"В»fВұВЈ"},{"u":"а¶§а·ҠвҖҚа¶»а·қ","f":"fg%da","i":"В»fВұВЈЕ "},{"u":"а¶§а·ҠвҖҚа¶»а·ӣ","f":"ffg%","i":"fВұа·ӣ"},{"u":"а¶§а·ҠвҖҚа¶»а·һ","f":"fg%!","i":"fВұа·һ"},{"u":"а¶§а·ҠвҖҚа¶»а¶Ӯ","f":"g%x","i":"fВұВ№"},{"u":"а¶§а·ҠвҖҚа¶»а¶ғ","f":"g%#","i":"fВұВә"},{"u":"а¶§а·ҠвҖҚа¶ә","f":"gH","i":"fВі"},{"u":"а¶§а·ҠвҖҚа¶»","f":"g%","i":"fВұ"},{"u":"а¶§а·Ҡ","f":"Гң","i":"G"},{"u":"а¶§а·Ҹ","f":"gd","i":"fВЈ"},{"u":"а¶§а·‘","f":"gE","i":"fВҰ"},{"u":"а¶§а·’","f":"ГЎ","i":"Г‘"},{"u":"а¶§а·“","f":"Г ","i":"Г’"},{"u":"а¶§а·”","f":"gq","i":"fВ§"},{"u":"а¶§а·–","f":"gQ","i":"fВ«"},{"u":"а¶§а·ҳ","f":"gD","i":"fВҜ"},{"u":"а¶§а·І","f":"gDD","i":"fВҜВҜ"},{"u":"а¶§а·ҹ","f":"g!","i":"fВ°"},{"u":"а¶§а·і","f":"g!","i":"fа·і"},{"u":"а¶§а·ҷ","f":"fg","i":"В»f"},{"u":"а¶§а·ҡ","f":"fГң","i":"В»G"},{"u":"а¶§а·ӣ","f":"ffg","i":"fа·ӣ"},{"u":"а¶§а·ң","f":"fgd","i":"В»fВЈ"},{"u":"а¶§а·қ","f":"fgda","i":"В»fВЈЕ "},{"u":"а¶§а·һ","f":"fg!","i":"В»fВ°"},{"u":"а¶§а¶Ӯ","f":"gx","i":"fВ№"},{"u":"а¶§а¶ғ","f":"g#","i":"fВә"},{"u":"а¶§","f":"g","i":"f"},{"u":"а¶Ёа·ҠвҖҚа¶әа·Ҹ","f":"GHd","i":"gВіВЈ"},{"u":"а¶Ёа·ҠвҖҚа¶әа·ң","f":"fGHd","i":"gВіа·ң"},{"u":"а¶Ёа·ҠвҖҚа¶әа·қ","f":"fGHda","i":"В»gВіВЈЕ "},{"u":"а¶Ёа·ҠвҖҚа¶»а·Ҹ","f":"G%d","i":"gВұВЈ"},{"u":"а¶Ёа·ҠвҖҚа¶»а·җ","f":"G%e","i":"gВұВҘ"},{"u":"а¶Ёа·ҠвҖҚа¶»а·‘","f":"G%E","i":"gВұВҰ"},{"u":"а¶Ёа·ҠвҖҚа¶»а·’","f":"G%s","i":"gВұвҖ№"},{"u":"а¶Ёа·ҠвҖҚа¶»а·“","f":"G%S","i":"gВұЕЎ"},{"u":"а¶Ёа·ҠвҖҚа¶»а·ҷ","f":"fG%","i":"gВұВ»"},{"u":"а¶Ёа·ҠвҖҚа¶»а·ҡ","f":"fG%a","i":"gВұа·ҡ"},{"u":"а¶Ёа·ҠвҖҚа¶»а·ң","f":"fG%d","i":"gВұа·ң"},{"u":"а¶Ёа·ҠвҖҚа¶»а·қ","f":"fG%da","i":"gВұа·қ"},{"u":"а¶Ёа·ҠвҖҚа¶»а·ӣ","f":"ffG%","i":"gВұа·ӣ"},{"u":"а¶Ёа·ҠвҖҚа¶»а·һ","f":"fG%!","i":"gВұа·һ"},{"u":"а¶Ёа·ҠвҖҚа¶»а¶Ӯ","f":"G%x","i":"gВұВ№"},{"u":"а¶Ёа·ҠвҖҚа¶»а¶ғ","f":"G%#","i":"gВұВә"},{"u":"а¶Ёа·ҠвҖҚа¶ә","f":"GH","i":"gВі"},{"u":"а¶Ёа·ҠвҖҚа¶»","f":"G%","i":"gВұ"},{"u":"а¶Ёа·Ҡ","f":"Ga","i":"gЕ "},{"u":"а¶Ёа·Ҹ","f":"Gd","i":"gВЈ"},{"u":"а¶Ёа·‘","f":"GE","i":"gВҰ"},{"u":"а¶Ёа·’","f":"ГҖ","i":"Г“"},{"u":"а¶Ёа·“","f":"ГҒ","i":"Г”"},{"u":"а¶Ёа·”","f":"Gq","i":"gВ§"},{"u":"а¶Ёа·–","f":"GQ","i":"gВ«"},{"u":"а¶Ёа·ҳ","f":"GD","i":"gВҜ"},{"u":"а¶Ёа·І","f":"GDD","i":"gВҜВҜ"},{"u":"а¶Ёа·ҹ","f":"G!","i":"gВ°"},{"u":"а¶Ёа·і","f":"G!","i":"gа·і"},{"u":"а¶Ёа·ҷ","f":"fG","i":"В»g"},{"u":"а¶Ёа·ҡ","f":"fGa","i":"В»gЕ "},{"u":"а¶Ёа·ӣ","f":"ffG","i":"gа·ӣ"},{"u":"а¶Ёа·ң","f":"fGd","i":"В»gВЈ"},{"u":"а¶Ёа·қ","f":"fGda","i":"В»gВЈЕ "},{"u":"а¶Ёа·һ","f":"fG!","i":"gа·һ"},{"u":"а¶Ёа¶Ӯ","f":"Gx","i":"gВ№"},{"u":"а¶Ёа¶ғ","f":"G#","i":"gВә"},{"u":"а¶Ё","f":"G","i":"g"},{"u":"а¶©а·ҠвҖҚа¶әа·Ҹ","f":"vHd","i":"hВіВЈ"},{"u":"а¶©а·ҠвҖҚа¶әа·ң","f":"fvHd","i":"В»hВіВЈ"},{"u":"а¶©а·ҠвҖҚа¶әа·қ","f":"fvHda","i":"В»ВіВЈЕ "},{"u":"а¶©а·ҠвҖҚа¶»а·Ҹ","f":"v%d","i":"hВұВЈ"},{"u":"а¶©а·ҠвҖҚа¶»а·җ","f":"v%e","i":"hВұВҘ"},{"u":"а¶©а·ҠвҖҚа¶»а·‘","f":"v%E","i":"hВұВҰ"},{"u":"а¶©а·ҠвҖҚа¶»а·’","f":"ГӨ%","i":"hВұвҖ№"},{"u":"а¶©а·ҠвҖҚа¶»а·“","f":"ГЈ%","i":"hВұЕЎ"},{"u":"а¶©а·ҠвҖҚа¶»а·ҷ","f":"fv%","i":"hВұВ»"},{"u":"а¶©а·ҠвҖҚа¶»а·ҡ","f":"fГў%","i":"В»Вұ"},{"u":"а¶©а·ҠвҖҚа¶»а·ң","f":"fv%d","i":"В»hВұВЈ"},{"u":"а¶©а·ҠвҖҚа¶»а·қ","f":"fv%da","i":"В»hВұВЈЕ "},{"u":"а¶©а·ҠвҖҚа¶»а·ӣ","f":"ffv%","i":"hВұа·ӣ"},{"u":"а¶©а·ҠвҖҚа¶»а·һ","f":"fv%!","i":"hВұа·һ"},{"u":"а¶©а·ҠвҖҚа¶»а¶Ӯ","f":"v%x","i":"hВұВ№"},{"u":"а¶©а·ҠвҖҚа¶»а¶ғ","f":"v%#","i":"hВұВә"},{"u":"а¶©а·ҠвҖҚа¶ә","f":"vH","i":"hВі"},{"u":"а¶©а·ҠвҖҚа¶»","f":"v%","i":"hВұ"},{"u":"а¶©а·Ҡ","f":"Гў","i":"H"},{"u":"а¶©а·Ҹ","f":"vd","i":"hВЈ"},{"u":"а¶©а·‘","f":"vE","i":"hВҰ"},{"u":"а¶©а·’","f":"ГӨ","i":"Г•"},{"u":"а¶©а·“","f":"ГЈ","i":"H"},{"u":"а¶©а·”","f":"vq","i":"hВ§"},{"u":"а¶©а·–","f":"vQ","i":"hВ«"},{"u":"а¶©а·ҳ","f":"vD","i":"hВҜ"},{"u":"а¶©а·І","f":"vDD","i":"hВҜВҜ"},{"u":"а¶©а·ҹ","f":"v!","i":"hВ°"},{"u":"а¶©а·і","f":"v!","i":"hа·і"},{"u":"а¶©а·ҷ","f":"fv","i":"В»h"},{"u":"а¶©а·ҡ","f":"fГў","i":"В»H"},{"u":"а¶©а·ӣ","f":"ffv","i":"hа·ӣ"},{"u":"а¶©а·ң","f":"fvd","i":"В»hВЈ"},{"u":"а¶©а·қ","f":"fvda","i":"В»hВЈЕ "},{"u":"а¶©а·һ","f":"fv!","i":"В»hВ°"},{"u":"а¶©а¶Ӯ","f":"vx","i":"hВ№"},{"u":"а¶©а¶ғ","f":"v#","i":"hВә"},{"u":"а¶©","f":"v","i":"h"},{"u":"а¶Әа·ҠвҖҚа¶әа·Ҹ","f":"VHd","i":"iВіВЈ"},{"u":"а¶Әа·ҠвҖҚа¶әа·ң","f":"fVHd","i":"iВіа·ң"},{"u":"а¶Әа·ҠвҖҚа¶әа·қ","f":"fVHda","i":"В»iВіВЈЕ "},{"u":"а¶Әа·ҠвҖҚа¶»а·Ҹ","f":"V%d","i":"iВұВЈ"},{"u":"а¶Әа·ҠвҖҚа¶»а·җ","f":"V%e","i":"iВұВҘ"},{"u":"а¶Әа·ҠвҖҚа¶»а·‘","f":"V%E","i":"iВұВҰ"},{"u":"а¶Әа·ҠвҖҚа¶»а·’","f":"V%s","i":"iВұвҖ№"},{"u":"а¶Әа·ҠвҖҚа¶»а·“","f":"V%S","i":"iВұЕЎ"},{"u":"а¶Әа·ҠвҖҚа¶»а·ҷ","f":"fV%","i":"iВұВ»"},{"u":"а¶Әа·ҠвҖҚа¶»а·ҡ","f":"fV%a","i":"iВұа·ҡ"},{"u":"а¶Әа·ҠвҖҚа¶»а·ң","f":"fV%d","i":"iВұа·ң"},{"u":"а¶Әа·ҠвҖҚа¶»а·қ","f":"fV%da","i":"iВұа·қ"},{"u":"а¶Әа·ҠвҖҚа¶»а·ӣ","f":"ffV%","i":"iВұа·ӣ"},{"u":"а¶Әа·ҠвҖҚа¶»а·һ","f":"fV%!","i":"iВұа·һ"},{"u":"а¶Әа·ҠвҖҚа¶»а¶Ӯ","f":"V%x","i":"iВұВ№"},{"u":"а¶Әа·ҠвҖҚа¶»а¶ғ","f":"V%#","i":"iВұВә"},{"u":"а¶Әа·ҠвҖҚа¶ә","f":"VH","i":"iВі"},{"u":"а¶Әа·ҠвҖҚа¶»","f":"V%","i":"iВұ"},{"u":"а¶Әа·Ҡ","f":"Va","i":"iЕ "},{"u":"а¶Әа·Ҹ","f":"Vd","i":"iВЈ"},{"u":"а¶Әа·‘","f":"VE","i":"iВҰ"},{"u":"а¶Әа·’","f":"ГҺ","i":"iвҖ№"},{"u":"а¶Әа·“","f":"Гҗ","i":"Гҷ"},{"u":"а¶Әа·”","f":"Vq","i":"iВ§"},{"u":"а¶Әа·–","f":"VQ","i":"iВ«"},{"u":"а¶Әа·ҳ","f":"VD","i":"iВҜ"},{"u":"а¶Әа·І","f":"VDD","i":"iВҜВҜ"},{"u":"а¶Әа·ҹ","f":"V!","i":"iВ°"},{"u":"а¶Әа·і","f":"V!","i":"iа·і"},{"u":"а¶Әа·ҷ","f":"fV","i":"В»i"},{"u":"а¶Әа·ҡ","f":"fVa","i":"В»вҖ”Е "},{"u":"а¶Әа·ӣ","f":"ffV","i":"iа·ӣ"},{"u":"а¶Әа·ң","f":"fVd","i":"В»iВЈ"},{"u":"а¶Әа·қ","f":"fVda","i":"В»iВЈЕ "},{"u":"а¶Әа·һ","f":"fV!","i":"iа·һ"},{"u":"а¶Әа¶Ӯ","f":"Vx","i":"iВ№"},{"u":"а¶Әа¶ғ","f":"V#","i":"iВә"},{"u":"а¶Ә","f":"V","i":"i"},{"u":"а¶«а·ҠвҖҚа¶әа·Ҹ","f":"KHd","i":"jВіВЈ"},{"u":"а¶«а·ҠвҖҚа¶әа·ң","f":"fKHd","i":"jВіа·ң"},{"u":"а¶«а·ҠвҖҚа¶әа·қ","f":"fKHda","i":"jВіа·қ"},{"u":"а¶«а·ҠвҖҚа¶»а·Ҹ","f":"K%d","i":"jВұВЈ"},{"u":"а¶«а·ҠвҖҚа¶»а·җ","f":"K%e","i":"jВұВҘ"},{"u":"а¶«а·ҠвҖҚа¶»а·‘","f":"K%E","i":"jВұВҰ"},{"u":"а¶«а·ҠвҖҚа¶»а·’","f":"K%s","i":"jВұвҖ№"},{"u":"а¶«а·ҠвҖҚа¶»а·“","f":"K%S","i":"jВұЕЎ"},{"u":"а¶«а·ҠвҖҚа¶»а·ҷ","f":"fK%","i":"jВұВ»"},{"u":"а¶«а·ҠвҖҚа¶»а·ҡ","f":"fK%a","i":"jВұа·ҡ"},{"u":"а¶«а·ҠвҖҚа¶»а·ң","f":"fK%d","i":"jВұа·ң"},{"u":"а¶«а·ҠвҖҚа¶»а·қ","f":"fK%da","i":"jВұа·қ"},{"u":"а¶«а·ҠвҖҚа¶»а·ӣ","f":"ffK%","i":"jВұа·ӣ"},{"u":"а¶«а·ҠвҖҚа¶»а·һ","f":"fK%!","i":"jВұа·һ"},{"u":"а¶«а·ҠвҖҚа¶»а¶Ӯ","f":"K%x","i":"jВұВ№"},{"u":"а¶«а·ҠвҖҚа¶»а¶ғ","f":"K%#","i":"jВұВә"},{"u":"а¶«а·ҠвҖҚа¶ә","f":"KH","i":"jВі"},{"u":"а¶«а·ҠвҖҚа¶»","f":"K%","i":"jВұ"},{"u":"а¶«а·Ҡ","f":"Ka","i":"jЕ "},{"u":"а¶«а·Ҹ","f":"Kd","i":"jВЈ"},{"u":"а¶«а·‘","f":"KE","i":"jВҰ"},{"u":"а¶«а·’","f":"вҖҡ","i":"jвҖ№"},{"u":"а¶«а·“","f":"Е’","i":"Гӣ"},{"u":"а¶«а·”","f":"Kq","i":"jВ§"},{"u":"а¶«а·–","f":"KQ","i":"jВ«"},{"u":"а¶«а·ҳ","f":"KD","i":"jВҜ"},{"u":"а¶«а·І","f":"KDD","i":"jВҜВҜ"},{"u":"а¶«а·ҹ","f":"K!","i":"jВ°"},{"u":"а¶«а·і","f":"K!","i":"jа·і"},{"u":"а¶«а·ҷ","f":"fK","i":"В»j"},{"u":"а¶«а·ҡ","f":"fKa","i":"В»jЕ "},{"u":"а¶«а·ӣ","f":"ffK","i":"jа·ӣ"},{"u":"а¶«а·ң","f":"fKd","i":"В»jВЈ"},{"u":"а¶«а·қ","f":"fKda","i":"В»jВЈЕ "},{"u":"а¶«а·һ","f":"fK!","i":"jа·һ"},{"u":"а¶«а¶Ӯ","f":"Kx","i":"jВ№"},{"u":"а¶«а¶ғ","f":"K#","i":"jВә"},{"u":"а¶«","f":"K","i":"j"},{"u":"а¶¬а·ҠвҖҚа¶әа·Ҹ","f":"~Hd","i":"а¶¬ВіВЈ"},{"u":"а¶¬а·ҠвҖҚа¶әа·ң","f":"f~Hd","i":"а¶¬Віа·ң"},{"u":"а¶¬а·ҠвҖҚа¶әа·қ","f":"f~Hda","i":"а¶¬Віа·қ"},{"u":"а¶¬а·ҠвҖҚа¶»а·Ҹ","f":"~%d","i":"а¶¬ВұВЈ"},{"u":"а¶¬а·ҠвҖҚа¶»а·җ","f":"~%e","i":"а¶¬ВұВҘ"},{"u":"а¶¬а·ҠвҖҚа¶»а·‘","f":"~%E","i":"а¶¬ВұВҰ"},{"u":"а¶¬а·ҠвҖҚа¶»а·’","f":"~%s","i":"а¶¬ВұвҖ№"},{"u":"а¶¬а·ҠвҖҚа¶»а·“","f":"~%S","i":"а¶¬ВұЕЎ"},{"u":"а¶¬а·ҠвҖҚа¶»а·ҷ","f":"f~%","i":"а¶¬ВұВ»"},{"u":"а¶¬а·ҠвҖҚа¶»а·ҡ","f":"f~%a","i":"а¶¬Вұа·ҡ"},{"u":"а¶¬а·ҠвҖҚа¶»а·ң","f":"f~%d","i":"а¶¬Вұа·ң"},{"u":"а¶¬а·ҠвҖҚа¶»а·қ","f":"f~%da","i":"а¶¬Вұа·қ"},{"u":"а¶¬а·ҠвҖҚа¶»а·ӣ","f":"ff~%","i":"а¶¬Вұа·ӣ"},{"u":"а¶¬а·ҠвҖҚа¶»а·һ","f":"f~%!","i":"а¶¬Вұа·һ"},{"u":"а¶¬а·ҠвҖҚа¶»а¶Ӯ","f":"~%x","i":"а¶¬ВұВ№"},{"u":"а¶¬а·ҠвҖҚа¶»а¶ғ","f":"~%#","i":"а¶¬ВұВә"},{"u":"а¶¬а·ҠвҖҚа¶ә","f":"~H","i":"а¶¬Ві"},{"u":"а¶¬а·ҠвҖҚа¶»","f":"~%","i":"а¶¬Вұ"},{"u":"а¶¬а·Ҡ","f":"ГҘ","i":"ВҫH"},{"u":"а¶¬а·Ҹ","f":"~d","i":"а¶¬ВЈ"},{"u":"а¶¬а·‘","f":"~E","i":"а¶¬ВҰ"},{"u":"а¶¬а·’","f":"Г§","i":"`vs"},{"u":"а¶¬а·“","f":"Г©","i":"ВҫГ–"},{"u":"а¶¬а·”","f":"~q","i":"а¶¬В§"},{"u":"а¶¬а·–","f":"~Q","i":"а¶¬В«"},{"u":"а¶¬а·ҳ","f":"~D","i":"а¶¬ВҜ"},{"u":"а¶¬а·І","f":"~DD","i":"а¶¬ВҜВҜ"},{"u":"а¶¬а·ҹ","f":"~!","i":"а¶¬В°"},{"u":"а¶¬а·і","f":"~!","i":"а¶¬а·і"},{"u":"а¶¬а·ҷ","f":"f~","i":"В»"},{"u":"а¶¬а·ҡ","f":"fГҘ","i":"В»ВҫH"},{"u":"а¶¬а·ӣ","f":"ff~","i":"а¶¬а·ӣ"},{"u":"а¶¬а·ң","f":"f~d","i":"В»ВЈ"},{"u":"а¶¬а·қ","f":"f~da","i":"В»ВЈЕ "},{"u":"а¶¬а·һ","f":"f~!","i":"а¶¬а·һ"},{"u":"а¶¬а¶Ӯ","f":"~x","i":"а¶¬В№"},{"u":"а¶¬а¶ғ","f":"~#","i":"а¶¬Вә"},{"u":"а¶¬","f":"~","i":"а¶¬"},{"u":"а¶ӯа·ҠвҖҚа¶әа·Ҹ","f":";Hd","i":"lВіВЈ"},{"u":"а¶ӯа·ҠвҖҚа¶әа·ң","f":"f;Hd","i":"В»lВіВЈ"},{"u":"а¶ӯа·ҠвҖҚа¶әа·қ","f":"f;Hda","i":"В»lВіВЈЕ "},{"u":"а¶ӯа·ҠвҖҚа¶»а·Ҹ","f":";%d","i":"lВұВЈ"},{"u":"а¶ӯа·ҠвҖҚа¶»а·җ","f":";%e","i":"lВұВҘ"},{"u":"а¶ӯа·ҠвҖҚа¶»а·‘","f":";%E","i":"lВұВҰ"},{"u":"а¶ӯа·ҠвҖҚа¶»а·’","f":";%s","i":"lВұвҖ№"},{"u":"а¶ӯа·ҠвҖҚа¶»а·“","f":";%S","i":"lВұЕЎ"},{"u":"а¶ӯа·ҠвҖҚа¶»а·ҷ","f":"f;%","i":"В»lВұ"},{"u":"а¶ӯа·ҠвҖҚа¶»а·ҡ","f":"f;%a","i":"В»lЕ Вұ"},{"u":"а¶ӯа·ҠвҖҚа¶»а·ң","f":"f;%d","i":"В»lВұВЈ"},{"u":"а¶ӯа·ҠвҖҚа¶»а·қ","f":"f;%da","i":"В»lВұВЈЕ "},{"u":"а¶ӯа·ҠвҖҚа¶»а·ӣ","f":"ff;%","i":"В»В»lВұ"},{"u":"а¶ӯа·ҠвҖҚа¶»а·һ","f":"f;%!","i":"lВұа·һ"},{"u":"а¶ӯа·ҠвҖҚа¶»а¶Ӯ","f":";%x","i":"lВұВ№"},{"u":"а¶ӯа·ҠвҖҚа¶»а¶ғ","f":";%#","i":"lВұВә"},{"u":"а¶ӯа·ҠвҖҚа¶ә","f":";H","i":"lВі"},{"u":"а¶ӯа·ҠвҖҚа¶»","f":";%","i":"lВұ"},{"u":"а¶ӯа·Ҡ","f":";a","i":"lЕ "},{"u":"а¶ӯа·Ҹ","f":";d","i":"lВЈ"},{"u":"а¶ӯа·‘","f":";E","i":"lВҰ"},{"u":"а¶ӯа·’","f":";s","i":"lвҖ№"},{"u":"а¶ӯа·“","f":";S","i":"lЕЎ"},{"u":"а¶ӯа·”","f":";=","i":"lВӘ"},{"u":"а¶ӯа·–","f":";+","i":"lВ®"},{"u":"а¶ӯа·ҳ","f":";D","i":"lВҜ"},{"u":"а¶ӯа·І","f":";DD","i":"lВҜВҜ"},{"u":"а¶ӯа·ҹ","f":";!","i":"lВ°"},{"u":"а¶ӯа·і","f":";!","i":"lа·і"},{"u":"а¶ӯа·ҷ","f":"f;","i":"В»l"},{"u":"а¶ӯа·ҡ","f":"f;a","i":"В»lЕ "},{"u":"а¶ӯа·ӣ","f":"ff;","i":"В»В»l"},{"u":"а¶ӯа·ң","f":"f;d","i":"В»lВЈ"},{"u":"а¶ӯа·қ","f":"f;da","i":"В»lВЈЕ "},{"u":"а¶ӯа·һ","f":"f;!","i":"В»lВ°"},{"u":"а¶ӯа¶Ӯ","f":";x","i":"lВ№"},{"u":"а¶ӯа¶ғ","f":";#","i":"lВә"},{"u":"а¶ӯ","f":";","i":"l"},{"u":"а¶®а·ҠвҖҚа¶әа·Ҹ","f":":Hd","i":"mВіВЈ"},{"u":"а¶®а·ҠвҖҚа¶әа·ң","f":"f:Hd","i":"В»mВіВЈ"},{"u":"а¶®а·ҠвҖҚа¶әа·қ","f":"f:Hda","i":"В»mВіВЈЕ "},{"u":"а¶®а·ҠвҖҚа¶»а·Ҹ","f":":%d","i":"mВұВЈ"},{"u":"а¶®а·ҠвҖҚа¶»а·җ","f":":%e","i":"mВұВҘ"},{"u":"а¶®а·ҠвҖҚа¶»а·‘","f":":%E","i":"mВұВҰ"},{"u":"а¶®а·ҠвҖҚа¶»а·’","f":":%s","i":"mВұвҖ№"},{"u":"а¶®а·ҠвҖҚа¶»а·“","f":":%S","i":"mВұЕЎ"},{"u":"а¶®а·ҠвҖҚа¶»а·ҷ","f":"f:%","i":"mВұВ»"},{"u":"а¶®а·ҠвҖҚа¶»а·ҡ","f":"f:%a","i":"mВұа·ҡ"},{"u":"а¶®а·ҠвҖҚа¶»а·ң","f":"f:%d","i":"mВұа·ң"},{"u":"а¶®а·ҠвҖҚа¶»а·қ","f":"f:%da","i":"mВұа·қ"},{"u":"а¶®а·ҠвҖҚа¶»а·ӣ","f":"ff:%","i":"mВұа·ӣ"},{"u":"а¶®а·ҠвҖҚа¶»а·һ","f":"f:%!","i":"mВұа·һ"},{"u":"а¶®а·ҠвҖҚа¶»а¶Ӯ","f":":%x","i":"mВұВ№"},{"u":"а¶®а·ҠвҖҚа¶»а¶ғ","f":":%#","i":"mВұВә"},{"u":"а¶®а·ҠвҖҚа¶ә","f":":H","i":"mВі"},{"u":"а¶®а·ҠвҖҚа¶»","f":":%","i":"mВұ"},{"u":"а¶®а·Ҡ","f":":a","i":"mЕ "},{"u":"а¶®а·Ҹ","f":":d","i":"mВЈ"},{"u":"а¶®а·‘","f":":E","i":"mВҰ"},{"u":"а¶®а·’","f":"Г“","i":"mвҖ№"},{"u":"а¶®а·“","f":"Г’","i":"Гһ"},{"u":"а¶®а·”","f":":q","i":"mВ§"},{"u":"а¶®а·–","f":":Q","i":"mВ«"},{"u":"а¶®а·ҳ","f":":D","i":"mВҜ"},{"u":"а¶®а·І","f":":DD","i":"mВҜВҜ"},{"u":"а¶®а·ҹ","f":":!","i":"mВ°"},{"u":"а¶®а·і","f":":!","i":"mа·і"},{"u":"а¶®а·ҷ","f":"f:","i":"В»m"},{"u":"а¶®а·ҡ","f":"f:a","i":"В»mЕ "},{"u":"а¶®а·ӣ","f":"ff:","i":"mа·ӣ"},{"u":"а¶®а·ң","f":"f:d","i":"В»mВЈ"},{"u":"а¶®а·қ","f":"f:da","i":"В»mВЈЕ "},{"u":"а¶®а·һ","f":"f:!","i":"mа·һ"},{"u":"а¶®а¶Ӯ","f":":x","i":"mВ№"},{"u":"а¶®а¶ғ","f":":#","i":"mВә"},{"u":"а¶®","f":":","i":"m"},{"u":"а¶Ҝа·ҠвҖҚа¶әа·Ҹ","f":"oHd","i":"nВіВЈ"},{"u":"а¶Ҝа·ҠвҖҚа¶әа·ң","f":"foHd","i":"В»nВіВЈ"},{"u":"а¶Ҝа·ҠвҖҚа¶әа·қ","f":"foHda","i":"В»nВіВЈЕ "},{"u":"а¶Ҝа·ҠвҖҚа¶»а·Ҹ","f":"Гёd","i":"nВұВЈ"},{"u":"а¶Ҝа·ҠвҖҚа¶»а·җ","f":"Гёe","i":"nВұВҘ"},{"u":"а¶Ҝа·ҠвҖҚа¶»а·‘","f":"ГёE","i":"nВұВҰ"},{"u":"а¶Ҝа·ҠвҖҚа¶»а·’","f":"Гёs","i":"nВұвҖ№"},{"u":"а¶Ҝа·ҠвҖҚа¶»а·“","f":"ГёS","i":"nВұЕЎ"},{"u":"а¶Ҝа·ҠвҖҚа¶»а·ҷ","f":"fГё","i":"В»"},{"u":"а¶Ҝа·ҠвҖҚа¶»а·ҡ","f":"fГёa","i":"В»Е "},{"u":"а¶Ҝа·ҠвҖҚа¶»а·ң","f":"fГёd","i":"В»ВЈ"},{"u":"а¶Ҝа·ҠвҖҚа¶»а·қ","f":"fГёda","i":"В»ВЈЕ "},{"u":"а¶Ҝа·ҠвҖҚа¶»а·ӣ","f":"ffГё","i":"nВұа·ӣ"},{"u":"а¶Ҝа·ҠвҖҚа¶»а·һ","f":"fГё!","i":"nВұа·һ"},{"u":"а¶Ҝа·ҠвҖҚа¶»а¶Ӯ","f":"Гёx","i":"nВұВ№"},{"u":"а¶Ҝа·ҠвҖҚа¶»а¶ғ","f":"Гё#","i":"nВұВә"},{"u":"а¶Ҝа·ҠвҖҚа¶ә","f":"oH","i":"nВі"},{"u":"а¶Ҝа·ҠвҖҚа¶»","f":"Гё","i":"nВұ"},{"u":"а¶Ҝа·Ҡ","f":"oa","i":"nЕ "},{"u":"а¶Ҝа·Ҹ","f":"od","i":"nВЈ"},{"u":"а¶Ҝа·‘","f":"oE","i":"nВҰ"},{"u":"а¶Ҝа·’","f":"ГҲ","i":"Вҙ"},{"u":"а¶Ҝа·“","f":"В§","i":"Вө"},{"u":"а¶Ҝа·”","f":"Гҝ","i":"ГЈ"},{"u":"а¶Ҝа·–","f":"ВҘ","i":"ГЈ"},{"u":"а¶Ҝа·ҳ","f":"oD","i":"nВҜ"},{"u":"а¶Ҝа·І","f":"oDD","i":"nВҜВҜ"},{"u":"а¶Ҝа·ҹ","f":"o!","i":"nВ°"},{"u":"а¶Ҝа·і","f":"o!","i":"nа·і"},{"u":"а¶Ҝа·ҷ","f":"fo","i":"В»n"},{"u":"а¶Ҝа·ҡ","f":"foa","i":"В»nЕ "},{"u":"а¶Ҝа·ӣ","f":"ffo","i":"В»В»n"},{"u":"а¶Ҝа·ң","f":"fod","i":"В»Г "},{"u":"а¶Ҝа·қ","f":"foda","i":"В»Г Е "},{"u":"а¶Ҝа·һ","f":"fo!","i":"В»nВ°"},{"u":"а¶Ҝа¶Ӯ","f":"ox","i":"nВ№"},{"u":"а¶Ҝа¶ғ","f":"o#","i":"nВә"},{"u":"а¶Ҝ","f":"o","i":"n"},{"u":"а¶°а·ҠвҖҚа¶әа·Ҹ","f":"OHd","i":"oВіВЈ"},{"u":"а¶°а·ҠвҖҚа¶әа·ң","f":"fOHd","i":"В»oВіВЈ"},{"u":"а¶°а·ҠвҖҚа¶әа·қ","f":"fOHda","i":"В»oВіВЈЕ "},{"u":"а¶°а·ҠвҖҚа¶»а·Ҹ","f":"O%d","i":"oВұВЈ"},{"u":"а¶°а·ҠвҖҚа¶»а·җ","f":"O%e","i":"oВұВҘ"},{"u":"а¶°а·ҠвҖҚа¶»а·‘","f":"O%E","i":"oВұВҰ"},{"u":"а¶°а·ҠвҖҚа¶»а·’","f":"ГӘ%","i":"oВұвҖ№"},{"u":"а¶°а·ҠвҖҚа¶»а·“","f":"Г«%","i":"oВұЕЎ"},{"u":"а¶°а·ҠвҖҚа¶»а·ҷ","f":"fO%","i":"В»oВұ"},{"u":"а¶°а·ҠвҖҚа¶»а·ҡ","f":"fГЁ%","i":"В»Вұ"},{"u":"а¶°а·ҠвҖҚа¶»а·ң","f":"fO%d","i":"oВұа·ң"},{"u":"а¶°а·ҠвҖҚа¶»а·қ","f":"fO%da","i":"oВұа·қ"},{"u":"а¶°а·ҠвҖҚа¶»а·ӣ","f":"ffO%","i":"oВұа·ӣ"},{"u":"а¶°а·ҠвҖҚа¶»а·һ","f":"fO%!","i":"oВұа·һ"},{"u":"а¶°а·ҠвҖҚа¶»а¶Ӯ","f":"O%x","i":"oВұВ№"},{"u":"а¶°а·ҠвҖҚа¶»а¶ғ","f":"O%#","i":"oВұВә"},{"u":"а¶°а·ҠвҖҚа¶ә","f":"OH","i":"oВі"},{"u":"а¶°а·ҠвҖҚа¶»","f":"O%","i":"oВұ"},{"u":"а¶°а·Ҡ","f":"ГЁ","i":"I"},{"u":"а¶°а·Ҹ","f":"Od","i":"oВЈ"},{"u":"а¶°а·‘","f":"OE","i":"oВҰ"},{"u":"а¶°а·’","f":"ГӘ","i":"Г©"},{"u":"а¶°а·“","f":"Г«","i":"ГӘ"},{"u":"а¶°а·”","f":"Oq","i":"oВ§"},{"u":"а¶°а·–","f":"OQ","i":"oВ«"},{"u":"а¶°а·ҳ","f":"OD","i":"oВҜ"},{"u":"а¶°а·І","f":"ODD","i":"oВҜВҜ"},{"u":"а¶°а·ҹ","f":"O!","i":"oВ°"},{"u":"а¶°а·і","f":"O!","i":"oа·і"},{"u":"а¶°а·ҷ","f":"fO","i":"В»o"},{"u":"а¶°а·ҡ","f":"fГЁ","i":"В»"},{"u":"а¶°а·ӣ","f":"ffO","i":"В»В»o"},{"u":"а¶°а·ң","f":"fOd","i":"В»oВЈ"},{"u":"а¶°а·қ","f":"fOda","i":"В»oВЈЕ "},{"u":"а¶°а·һ","f":"fO!","i":"oа·һ"},{"u":"а¶°а¶Ӯ","f":"Ox","i":"oВ№"},{"u":"а¶°а¶ғ","f":"O#","i":"oВә"},{"u":"а¶°","f":"O","i":"o"},{"u":"а¶ұа·ҠвҖҚа¶әа·Ҹ","f":"kHd","i":"pВіВЈ"},{"u":"а¶ұа·ҠвҖҚа¶әа·ң","f":"fkHd","i":"pВіа·ң"},{"u":"а¶ұа·ҠвҖҚа¶әа·қ","f":"fkHda","i":"В»pВіВЈЕ "},{"u":"а¶ұа·ҠвҖҚа¶»а·Ҹ","f":"k%d","i":"pВұВЈ"},{"u":"а¶ұа·ҠвҖҚа¶»а·җ","f":"k%e","i":"pВұВҘ"},{"u":"а¶ұа·ҠвҖҚа¶»а·‘","f":"k%E","i":"pВұВҰ"},{"u":"а¶ұа·ҠвҖҚа¶»а·’","f":"k%s","i":"pВұвҖ№"},{"u":"а¶ұа·ҠвҖҚа¶»а·“","f":"k%S","i":"pВұЕЎ"},{"u":"а¶ұа·ҠвҖҚа¶»а·ҷ","f":"fk%","i":"pВұВ»"},{"u":"а¶ұа·ҠвҖҚа¶»а·ҡ","f":"fk%a","i":"pВұа·ҡ"},{"u":"а¶ұа·ҠвҖҚа¶»а·ң","f":"fk%d","i":"pВұа·ң"},{"u":"а¶ұа·ҠвҖҚа¶»а·қ","f":"fk%da","i":"pВұа·қ"},{"u":"а¶ұа·ҠвҖҚа¶»а·ӣ","f":"ffk%","i":"pВұа·ӣ"},{"u":"а¶ұа·ҠвҖҚа¶»а·һ","f":"fk%!","i":"pВұа·һ"},{"u":"а¶ұа·ҠвҖҚа¶»а¶Ӯ","f":"k%x","i":"pВұВ№"},{"u":"а¶ұа·ҠвҖҚа¶»а¶ғ","f":"k%#","i":"pВұВә"},{"u":"а¶ұа·ҠвҖҚа¶ә","f":"kH","i":"pВі"},{"u":"а¶ұа·ҠвҖҚа¶»","f":"k%","i":"pВұ"},{"u":"а¶ұа·Ҡ","f":"ka","i":"pЕ "},{"u":"а¶ұа·Ҹ","f":"kd","i":"pВЈ"},{"u":"а¶ұа·‘","f":"kE","i":"pВҰ"},{"u":"а¶ұа·’","f":"ks","i":"pвҖ№"},{"u":"а¶ұа·“","f":"kS","i":"pЕЎ"},{"u":"а¶ұа·”","f":"kq","i":"pВ§"},{"u":"а¶ұа·–","f":"kQ","i":"pВ«"},{"u":"а¶ұа·ҳ","f":"kD","i":"pВҜ"},{"u":"а¶ұа·І","f":"kDD","i":"pВҜВҜ"},{"u":"а¶ұа·ҹ","f":"k!","i":"pВ°"},{"u":"а¶ұа·і","f":"k!","i":"pа·і"},{"u":"а¶ұа·ҷ","f":"fk","i":"В»p"},{"u":"а¶ұа·ҡ","f":"fka","i":"В»pЕ "},{"u":"а¶ұа·ӣ","f":"ffk","i":"В»В»p"},{"u":"а¶ұа·ң","f":"fkd","i":"В»pВЈ"},{"u":"а¶ұа·қ","f":"fkda","i":"В»pВЈЕ "},{"u":"а¶ұа·һ","f":"fk!","i":"В»pВ°"},{"u":"а¶ұа¶Ӯ","f":"kx","i":"pВ№"},{"u":"а¶ұа¶ғ","f":"k#","i":"pВә"},{"u":"а¶ұ","f":"k","i":"p"},{"u":"а¶іа·ҠвҖҚа¶әа·Ҹ","f":"|Hd","i":"qВіВЈ"},{"u":"а¶іа·ҠвҖҚа¶әа·ң","f":"f|Hd","i":"qВіа·ң"},{"u":"а¶іа·ҠвҖҚа¶әа·қ","f":"f|Hda","i":"qВіа·қ"},{"u":"а¶іа·ҠвҖҚа¶»а·Ҹ","f":"|%d","i":"qВұВЈ"},{"u":"а¶іа·ҠвҖҚа¶»а·җ","f":"|%e","i":"qВұВҘ"},{"u":"а¶іа·ҠвҖҚа¶»а·‘","f":"|%E","i":"qВұВҰ"},{"u":"а¶іа·ҠвҖҚа¶»а·’","f":"|%s","i":"qВұвҖ№"},{"u":"а¶іа·ҠвҖҚа¶»а·“","f":"|%S","i":"qВұЕЎ"},{"u":"а¶іа·ҠвҖҚа¶»а·ҷ","f":"f|%","i":"qВұВ»"},{"u":"а¶іа·ҠвҖҚа¶»а·ҡ","f":"f|%a","i":"qВұа·ҡ"},{"u":"а¶іа·ҠвҖҚа¶»а·ң","f":"f|%d","i":"qВұа·ң"},{"u":"а¶іа·ҠвҖҚа¶»а·қ","f":"f|%da","i":"qВұа·қ"},{"u":"а¶іа·ҠвҖҚа¶»а·ӣ","f":"ff|%","i":"qВұа·ӣ"},{"u":"а¶іа·ҠвҖҚа¶»а·һ","f":"f|%!","i":"qВұа·һ"},{"u":"а¶іа·ҠвҖҚа¶»а¶Ӯ","f":"|%x","i":"qВұВ№"},{"u":"а¶іа·ҠвҖҚа¶»а¶ғ","f":"|%#","i":"qВұВә"},{"u":"а¶іа·ҠвҖҚа¶ә","f":"|H","i":"qВі"},{"u":"а¶іа·ҠвҖҚа¶»","f":"|%","i":"qВұ"},{"u":"а¶іа·Ҡ","f":"|a","i":"qЕ "},{"u":"а¶іа·Ҹ","f":"|d","i":"qВЈ"},{"u":"а¶іа·‘","f":"|E","i":"qВҰ"},{"u":"а¶іа·’","f":"Вў","i":"qвҖ№"},{"u":"а¶іа·“","f":"ВЈ","i":"qЕЎ"},{"u":"а¶іа·”","f":"Г·","i":"ВҫГЈ"},{"u":"а¶іа·–","f":"ВӘ","i":"ВҫГӨ"},{"u":"а¶іа·ҳ","f":"|D","i":"qВҜ"},{"u":"а¶іа·І","f":"|DD","i":"qВҜВҜ"},{"u":"а¶іа·ҹ","f":"|!","i":"qВ°"},{"u":"а¶іа·і","f":"|!","i":"qа·і"},{"u":"а¶іа·ҷ","f":"f|","i":"В»Вҫn"},{"u":"а¶іа·ҡ","f":"f|a","i":"В»qЕ "},{"u":"а¶іа·ӣ","f":"ff|","i":"qа·ӣ"},{"u":"а¶іа·ң","f":"f|d","i":"В»qВЈ"},{"u":"а¶іа·қ","f":"f|da","i":"В»qВЈЕ "},{"u":"а¶іа·һ","f":"f|!","i":"qа·һ"},{"u":"а¶іа¶Ӯ","f":"|x","i":"qВ№"},{"u":"а¶іа¶ғ","f":"|#","i":"qВә"},{"u":"а¶і","f":"|","i":"q"},{"u":"а¶ҙа·ҠвҖҚа¶әа·Ҹ","f":"mHd","i":"rВіВЈ"},{"u":"а¶ҙа·ҠвҖҚа¶әа·ң","f":"fmHd","i":"В»rВіВЈ"},{"u":"а¶ҙа·ҠвҖҚа¶әа·қ","f":"fmHda","i":"В»rВіВЈЕ "},{"u":"а¶ҙа·ҠвҖҚа¶»а·Ҹ","f":"m%d","i":"rВұВЈ"},{"u":"а¶ҙа·ҠвҖҚа¶»а·җ","f":"m%e","i":"rВұВҘ"},{"u":"а¶ҙа·ҠвҖҚа¶»а·‘","f":"m%E","i":"rВұВҰ"},{"u":"а¶ҙа·ҠвҖҚа¶»а·’","f":"m%s","i":"rВұвҖ№"},{"u":"а¶ҙа·ҠвҖҚа¶»а·“","f":"m%S","i":"rВұЕЎ"},{"u":"а¶ҙа·ҠвҖҚа¶»а·ҷ","f":"fm%","i":"В»rВұ"},{"u":"а¶ҙа·ҠвҖҚа¶»а·ҡ","f":"fm%a","i":"В»rЕ Вұ"},{"u":"а¶ҙа·ҠвҖҚа¶»а·ң","f":"fm%d","i":"В»rВұВЈ"},{"u":"а¶ҙа·ҠвҖҚа¶»а·қ","f":"fm%da","i":"В»rВұВЈЕ "},{"u":"а¶ҙа·ҠвҖҚа¶»а·ӣ","f":"ffm%","i":"rВұа·ӣ"},{"u":"а¶ҙа·ҠвҖҚа¶»а·һ","f":"fm%!","i":"В»rВұВ°"},{"u":"а¶ҙа·ҠвҖҚа¶»а¶Ӯ","f":"m%x","i":"rВұВ№"},{"u":"а¶ҙа·ҠвҖҚа¶»а¶ғ","f":"m%#","i":"rВұВә"},{"u":"а¶ҙа·ҠвҖҚа¶ә","f":"mH","i":"rВі"},{"u":"а¶ҙа·ҠвҖҚа¶»","f":"m%","i":"rВұ"},{"u":"а¶ҙа·Ҡ","f":"ma","i":"rЕ "},{"u":"а¶ҙа·Ҹ","f":"md","i":"rВЈ"},{"u":"а¶ҙа·‘","f":"mE","i":"rВҰ"},{"u":"а¶ҙа·’","f":"ms","i":"rвҖ№"},{"u":"а¶ҙа·“","f":"mS","i":"rЕЎ"},{"u":"а¶ҙа·”","f":"mq","i":"rВ§"},{"u":"а¶ҙа·–","f":"mQ","i":"rВ«"},{"u":"а¶ҙа·ҳ","f":"mD","i":"rВҜ"},{"u":"а¶ҙа·І","f":"mDD","i":"rВҜВҜ"},{"u":"а¶ҙа·ҹ","f":"m!","i":"rВ°"},{"u":"а¶ҙа·і","f":"m!","i":"rа·і"},{"u":"а¶ҙа·ҷ","f":"fm","i":"В»r"},{"u":"а¶ҙа·ҡ","f":"fma","i":"В»rЕ "},{"u":"а¶ҙа·ӣ","f":"ffm","i":"В»В»r"},{"u":"а¶ҙа·ң","f":"fmd","i":"В»rВЈ"},{"u":"а¶ҙа·қ","f":"fmda","i":"В»rВЈЕ "},{"u":"а¶ҙа·һ","f":"fm!","i":"В»rВ°"},{"u":"а¶ҙа¶Ӯ","f":"mx","i":"rВ№"},{"u":"а¶ҙа¶ғ","f":"m#","i":"rВә"},{"u":"а¶ҙ","f":"m","i":"r"},{"u":"а¶өа·ҠвҖҚа¶әа·Ҹ","f":"MHd","i":"sВіВЈ"},{"u":"а¶өа·ҠвҖҚа¶әа·ң","f":"fMHd","i":"sВіа·ң"},{"u":"а¶өа·ҠвҖҚа¶әа·қ","f":"fMHda","i":"В»sВіВЈЕ "},{"u":"а¶өа·ҠвҖҚа¶»а·Ҹ","f":"M%d","i":"sВұВЈ"},{"u":"а¶өа·ҠвҖҚа¶»а·җ","f":"M%e","i":"sВұВҘ"},{"u":"а¶өа·ҠвҖҚа¶»а·‘","f":"M%E","i":"sВұВҰ"},{"u":"а¶өа·ҠвҖҚа¶»а·’","f":"M%s","i":"sВұвҖ№"},{"u":"а¶өа·ҠвҖҚа¶»а·“","f":"M%S","i":"sВұЕЎ"},{"u":"а¶өа·ҠвҖҚа¶»а·ҷ","f":"fM%","i":"sВұВ»"},{"u":"а¶өа·ҠвҖҚа¶»а·ҡ","f":"fM%a","i":"sВұа·ҡ"},{"u":"а¶өа·ҠвҖҚа¶»а·ң","f":"fM%d","i":"sВұа·ң"},{"u":"а¶өа·ҠвҖҚа¶»а·қ","f":"fM%da","i":"sВұа·қ"},{"u":"а¶өа·ҠвҖҚа¶»а·ӣ","f":"ffM%","i":"sВұа·ӣ"},{"u":"а¶өа·ҠвҖҚа¶»а·һ","f":"fM%!","i":"sВұа·һ"},{"u":"а¶өа·ҠвҖҚа¶»а¶Ӯ","f":"M%x","i":"sВұВ№"},{"u":"а¶өа·ҠвҖҚа¶»а¶ғ","f":"M%#","i":"sВұВә"},{"u":"а¶өа·ҠвҖҚа¶ә","f":"MH","i":"sВі"},{"u":"а¶өа·ҠвҖҚа¶»","f":"M%","i":"sВұ"},{"u":"а¶өа·Ҡ","f":"Ma","i":"sЕ "},{"u":"а¶өа·Ҹ","f":"Md","i":"sВЈ"},{"u":"а¶өа·‘","f":"ME","i":"sВҰ"},{"u":"а¶өа·’","f":"Гқ","i":"Гӯ"},{"u":"а¶өа·“","f":"Гҡ","i":"Г®"},{"u":"а¶өа·”","f":"Mq","i":"sВ§"},{"u":"а¶өа·–","f":"MQ","i":"sВ«"},{"u":"а¶өа·ҳ","f":"MD","i":"sВҜ"},{"u":"а¶өа·І","f":"MDD","i":"sВҜВҜ"},{"u":"а¶өа·ҹ","f":"M!","i":"sВ°"},{"u":"а¶өа·і","f":"M!","i":"sа·і"},{"u":"а¶өа·ҷ","f":"fM","i":"В»s"},{"u":"а¶өа·ҡ","f":"fMa","i":"В»sЕ "},{"u":"а¶өа·ӣ","f":"ffM","i":"sа·ӣ"},{"u":"а¶өа·ң","f":"fMd","i":"В»sВЈ"},{"u":"а¶өа·қ","f":"fMda","i":"В»sВЈЕ "},{"u":"а¶өа·һ","f":"fM!","i":"sа·һ"},{"u":"а¶өа¶Ӯ","f":"Mx","i":"sВ№"},{"u":"а¶өа¶ғ","f":"M#","i":"sВә"},{"u":"а¶ө","f":"M","i":"s"},{"u":"а¶¶а·ҠвҖҚа¶әа·Ҹ","f":"nHd","i":"tВіВЈ"},{"u":"а¶¶а·ҠвҖҚа¶әа·ң","f":"fnHd","i":"В»tВіВЈ"},{"u":"а¶¶а·ҠвҖҚа¶әа·қ","f":"fnHda","i":"В»tВіВЈЕ "},{"u":"а¶¶а·ҠвҖҚа¶»а·Ҹ","f":"n%d","i":"tВұВЈ"},{"u":"а¶¶а·ҠвҖҚа¶»а·җ","f":"n%e","i":"tВұВҘ"},{"u":"а¶¶а·ҠвҖҚа¶»а·‘","f":"n%E","i":"tВұВҰ"},{"u":"а¶¶а·ҠвҖҚа¶»а·’","f":"Г¬%","i":"tВұвҖ№"},{"u":"а¶¶а·ҠвҖҚа¶»а·“","f":"Г®%","i":"tВұЕЎ"},{"u":"а¶¶а·ҠвҖҚа¶»а·ҷ","f":"fn%","i":"В»tВұ"},{"u":"а¶¶а·ҠвҖҚа¶»а·ҡ","f":"fГӯ%","i":"В»Вұ"},{"u":"а¶¶а·ҠвҖҚа¶»а·ң","f":"fn%d","i":"tВұа·ң"},{"u":"а¶¶а·ҠвҖҚа¶»а·қ","f":"fn%da","i":"В»tВұВЈЕ "},{"u":"а¶¶а·ҠвҖҚа¶»а·ӣ","f":"ffn%","i":"tВұа·ӣ"},{"u":"а¶¶а·ҠвҖҚа¶»а·һ","f":"fn%!","i":"tВұа·һ"},{"u":"а¶¶а·ҠвҖҚа¶»а¶Ӯ","f":"n%x","i":"tВұВ№"},{"u":"а¶¶а·ҠвҖҚа¶»а¶ғ","f":"n%#","i":"tВұВә"},{"u":"а¶¶а·ҠвҖҚа¶ә","f":"nH","i":"tВі"},{"u":"а¶¶а·ҠвҖҚа¶»","f":"n%","i":"tВұ"},{"u":"а¶¶а·Ҡ","f":"Гӯ","i":"J"},{"u":"а¶¶а·Ҹ","f":"nd","i":"tВЈ"},{"u":"а¶¶а·‘","f":"nE","i":"tВҰ"},{"u":"а¶¶а·’","f":"Г¬","i":"ГҜ"},{"u":"а¶¶а·“","f":"Г®","i":"Г°"},{"u":"а¶¶а·”","f":"nq","i":"tВ§"},{"u":"а¶¶а·–","f":"nQ","i":"tВ«"},{"u":"а¶¶а·ҳ","f":"nD","i":"tВҜ"},{"u":"а¶¶а·І","f":"nDD","i":"tВҜВҜ"},{"u":"а¶¶а·ҹ","f":"n!","i":"tВ°"},{"u":"а¶¶а·і","f":"n!","i":"tа·і"},{"u":"а¶¶а·ҷ","f":"fn","i":"В»t"},{"u":"а¶¶а·ҡ","f":"fГӯ","i":"В»J"},{"u":"а¶¶а·ӣ","f":"ffn","i":"tа·ӣ"},{"u":"а¶¶а·ң","f":"fnd","i":"В»tВЈ"},{"u":"а¶¶а·қ","f":"fnda","i":"В»tВЈЕ "},{"u":"а¶¶а·һ","f":"fn!","i":"В»tВ°"},{"u":"а¶¶а¶Ӯ","f":"nx","i":"tВ№"},{"u":"а¶¶а¶ғ","f":"n#","i":"tВә"},{"u":"а¶¶","f":"n","i":"t"},{"u":"а¶·а·ҠвҖҚа¶әа·Ҹ","f":"NHd","i":"uВіВЈ"},{"u":"а¶·а·ҠвҖҚа¶әа·ң","f":"fNHd","i":"В»uВіВЈ"},{"u":"а¶·а·ҠвҖҚа¶әа·қ","f":"fNHda","i":"В»uВіВЈЕ "},{"u":"а¶·а·ҠвҖҚа¶»а·Ҹ","f":"N%d","i":"uВұВЈ"},{"u":"а¶·а·ҠвҖҚа¶»а·җ","f":"N%e","i":"uВұВҘ"},{"u":"а¶·а·ҠвҖҚа¶»а·‘","f":"N%E","i":"uВұВҰ"},{"u":"а¶·а·ҠвҖҚа¶»а·’","f":"N%s","i":"uВұвҖ№"},{"u":"а¶·а·ҠвҖҚа¶»а·“","f":"N%S","i":"uВұЕЎ"},{"u":"а¶·а·ҠвҖҚа¶»а·ҷ","f":"fN%","i":"В»uВұ"},{"u":"а¶·а·ҠвҖҚа¶»а·ҡ","f":"fN%a","i":"uВұа·ҡ"},{"u":"а¶·а·ҠвҖҚа¶»а·ң","f":"fN%d","i":"uВұа·ң"},{"u":"а¶·а·ҠвҖҚа¶»а·қ","f":"fN%da","i":"uВұа·қ"},{"u":"а¶·а·ҠвҖҚа¶»а·ӣ","f":"ffN%","i":"uВұа·ӣ"},{"u":"а¶·а·ҠвҖҚа¶»а·һ","f":"fN%!","i":"uВұа·һ"},{"u":"а¶·а·ҠвҖҚа¶»а¶Ӯ","f":"N%x","i":"uВұВ№"},{"u":"а¶·а·ҠвҖҚа¶»а¶ғ","f":"N%#","i":"uВұВә"},{"u":"а¶·а·ҠвҖҚа¶ә","f":"NH","i":"uВі"},{"u":"а¶·а·ҠвҖҚа¶»","f":"N%","i":"uВұ"},{"u":"а¶·а·Ҡ","f":"Na","i":"uЕ "},{"u":"а¶·а·Ҹ","f":"Nd","i":"uВЈ"},{"u":"а¶·а·‘","f":"NE","i":"uВҰ"},{"u":"а¶·а·’","f":"Ns","i":"uвҖ№"},{"u":"а¶·а·“","f":"NS","i":"uЕЎ"},{"u":"а¶·а·”","f":"N=","i":"uВ§"},{"u":"а¶·а·–","f":"N+","i":"uВ«"},{"u":"а¶·а·ҳ","f":"ND","i":"uВҜ"},{"u":"а¶·а·І","f":"NDD","i":"uВҜВҜ"},{"u":"а¶·а·ҹ","f":"N!","i":"uВ°"},{"u":"а¶·а·і","f":"N!","i":"uа·і"},{"u":"а¶·а·ҷ","f":"fN","i":"В»u"},{"u":"а¶·а·ҡ","f":"fNa","i":"В»uЕ "},{"u":"а¶·а·ӣ","f":"ffN","i":"uа·ӣ"},{"u":"а¶·а·ң","f":"fNd","i":"В»uВЈ"},{"u":"а¶·а·қ","f":"fNda","i":"В»uВЈЕ "},{"u":"а¶·а·һ","f":"fN!","i":"В»uВ°"},{"u":"а¶·а¶Ӯ","f":"Nx","i":"uВ№"},{"u":"а¶·а¶ғ","f":"N#","i":"uВә"},{"u":"а¶·","f":"N","i":"u"},{"u":"а¶ёа·ҠвҖҚа¶әа·Ҹ","f":"uHd","i":"vВіВЈ"},{"u":"а¶ёа·ҠвҖҚа¶әа·ң","f":"fuHd","i":"В»vВіВЈ"},{"u":"а¶ёа·ҠвҖҚа¶әа·қ","f":"fuHda","i":"В»vВіВЈЕ "},{"u":"а¶ёа·ҠвҖҚа¶»а·Ҹ","f":"u%d","i":"vВұВЈ"},{"u":"а¶ёа·ҠвҖҚа¶»а·җ","f":"u%e","i":"vВұВҘ"},{"u":"а¶ёа·ҠвҖҚа¶»а·‘","f":"u%E","i":"vВұВҰ"},{"u":"а¶ёа·ҠвҖҚа¶»а·’","f":"Гұ%","i":"vВұвҖ№"},{"u":"а¶ёа·ҠвҖҚа¶»а·“","f":"Гі%","i":"vВұЕЎ"},{"u":"а¶ёа·ҠвҖҚа¶»а·ҷ","f":"fu%","i":"vВұВ»"},{"u":"а¶ёа·ҠвҖҚа¶»а·ҡ","f":"fГҜ%","i":"vВұа·ҡ"},{"u":"а¶ёа·ҠвҖҚа¶»а·ң","f":"fu%d","i":"vВұа·ң"},{"u":"а¶ёа·ҠвҖҚа¶»а·қ","f":"fu%da","i":"vВұа·қ"},{"u":"а¶ёа·ҠвҖҚа¶»а·ӣ","f":"ffu%","i":"vВұа·ӣ"},{"u":"а¶ёа·ҠвҖҚа¶»а·һ","f":"fu%!","i":"vВұа·һ"},{"u":"а¶ёа·ҠвҖҚа¶»а¶Ӯ","f":"u%x","i":"vВұВ№"},{"u":"а¶ёа·ҠвҖҚа¶»а¶ғ","f":"u%#","i":"vВұВә"},{"u":"а¶ёа·ҠвҖҚа¶ә","f":"uH","i":"vВі"},{"u":"а¶ёа·ҠвҖҚа¶»","f":"u%","i":"vВұ"},{"u":"а¶ёа·Ҡ","f":"ГҜ","i":"K"},{"u":"а¶ёа·Ҹ","f":"ud","i":"vВЈ"},{"u":"а¶ёа·‘","f":"uE","i":"vВҰ"},{"u":"а¶ёа·’","f":"Гұ","i":"Гұ"},{"u":"а¶ёа·“","f":"Гі","i":"ГІ"},{"u":"а¶ёа·”","f":"uq","i":"vВ§"},{"u":"а¶ёа·–","f":"uQ","i":"vВ«"},{"u":"а¶ёа·ҳ","f":"uD","i":"vВҜ"},{"u":"а¶ёа·І","f":"uDD","i":"vВҜВҜ"},{"u":"а¶ёа·ҹ","f":"u!","i":"vВ°"},{"u":"а¶ёа·і","f":"u!","i":"vа·і"},{"u":"а¶ёа·ҷ","f":"fu","i":"В»v"},{"u":"а¶ёа·ҡ","f":"fГҜ","i":"В»K"},{"u":"а¶ёа·ӣ","f":"ffu","i":"В»В»v"},{"u":"а¶ёа·ң","f":"fud","i":"В»vВЈ"},{"u":"а¶ёа·қ","f":"fuda","i":"В»vВЈЕ "},{"u":"а¶ёа·һ","f":"fu!","i":"В»vВ°"},{"u":"а¶ёа¶Ӯ","f":"ux","i":"vВ№"},{"u":"а¶ёа¶ғ","f":"u#","i":"vВә"},{"u":"а¶ё","f":"u","i":"v"},{"u":"а¶№а·ҠвҖҚа¶әа·Ҹ","f":"UHd","i":"wВіВЈ"},{"u":"а¶№а·ҠвҖҚа¶әа·ң","f":"fUHd","i":"wВіа·ң"},{"u":"а¶№а·ҠвҖҚа¶әа·қ","f":"fUHda","i":"wВіа·қ"},{"u":"а¶№а·ҠвҖҚа¶»а·Ҹ","f":"U%d","i":"wВұВЈ"},{"u":"а¶№а·ҠвҖҚа¶»а·җ","f":"U%e","i":"wВұВҘ"},{"u":"а¶№а·ҠвҖҚа¶»а·‘","f":"U%E","i":"wВұВҰ"},{"u":"а¶№а·ҠвҖҚа¶»а·’","f":"Гҙ%","i":"wВұвҖ№"},{"u":"а¶№а·ҠвҖҚа¶»а·“","f":"Г¶%","i":"wВұЕЎ"},{"u":"а¶№а·ҠвҖҚа¶»а·ҷ","f":"fU%","i":"wВұВ»"},{"u":"а¶№а·ҠвҖҚа¶»а·ҡ","f":"fГІ%","i":"wВұа·ҡ"},{"u":"а¶№а·ҠвҖҚа¶»а·ң","f":"fU%d","i":"wВұа·ң"},{"u":"а¶№а·ҠвҖҚа¶»а·қ","f":"fU%da","i":"wВұа·қ"},{"u":"а¶№а·ҠвҖҚа¶»а·ӣ","f":"ffU%","i":"wВұа·ӣ"},{"u":"а¶№а·ҠвҖҚа¶»а·һ","f":"fU%!","i":"wВұа·һ"},{"u":"а¶№а·ҠвҖҚа¶»а¶Ӯ","f":"U%x","i":"wВұВ№"},{"u":"а¶№а·ҠвҖҚа¶»а¶ғ","f":"U%#","i":"wВұВә"},{"u":"а¶№а·ҠвҖҚа¶ә","f":"UH","i":"wВі"},{"u":"а¶№а·ҠвҖҚа¶»","f":"U%","i":"wВұ"},{"u":"а¶№а·Ҡ","f":"ГІ","i":"L"},{"u":"а¶№а·Ҹ","f":"Ud","i":"wВЈ"},{"u":"а¶№а·‘","f":"UE","i":"wВҰ"},{"u":"а¶№а·’","f":"Гҙ","i":"Гі"},{"u":"а¶№а·“","f":"Г¶","i":"Гҙ"},{"u":"а¶№а·”","f":"Uq","i":"wВ§"},{"u":"а¶№а·–","f":"UQ","i":"wВ«"},{"u":"а¶№а·ҳ","f":"UD","i":"wВҜ"},{"u":"а¶№а·І","f":"UDD","i":"wВҜВҜ"},{"u":"а¶№а·ҹ","f":"U!","i":"wВ°"},{"u":"а¶№а·і","f":"U!","i":"wа·і"},{"u":"а¶№а·ҷ","f":"fU","i":"В»w"},{"u":"а¶№а·ҡ","f":"fГІ","i":"В»L"},{"u":"а¶№а·ӣ","f":"ffU","i":"wа·ӣ"},{"u":"а¶№а·ң","f":"fUd","i":"В»wВЈ"},{"u":"а¶№а·қ","f":"fUda","i":"В»wВЈЕ "},{"u":"а¶№а·һ","f":"fU!","i":"wа·һ"},{"u":"а¶№а¶Ӯ","f":"Ux","i":"wВ№"},{"u":"а¶№а¶ғ","f":"U#","i":"wВә"},{"u":"а¶№","f":"U","i":"w"},{"u":"а¶әа·ҠвҖҚа¶әа·Ҹ","f":"hHd","i":"xВіВЈ"},{"u":"а¶әа·ҠвҖҚа¶әа·ң","f":"fhHd","i":"xВіа·ң"},{"u":"а¶әа·ҠвҖҚа¶әа·қ","f":"fhHda","i":"xВіа·қ"},{"u":"а¶әа·ҠвҖҚа¶»а·Ҹ","f":"h%d","i":"xВұВЈ"},{"u":"а¶әа·ҠвҖҚа¶»а·җ","f":"h%e","i":"xВұВҘ"},{"u":"а¶әа·ҠвҖҚа¶»а·‘","f":"h%E","i":"xВұВҰ"},{"u":"а¶әа·ҠвҖҚа¶»а·’","f":"h%s","i":"xВұвҖ№"},{"u":"а¶әа·ҠвҖҚа¶»а·“","f":"h%S","i":"xВұЕЎ"},{"u":"а¶әа·ҠвҖҚа¶»а·ҷ","f":"fh%","i":"xВұВ»"},{"u":"а¶әа·ҠвҖҚа¶»а·ҡ","f":"fh%a","i":"xВұа·ҡ"},{"u":"а¶әа·ҠвҖҚа¶»а·ң","f":"fh%d","i":"xВұа·ң"},{"u":"а¶әа·ҠвҖҚа¶»а·қ","f":"fh%da","i":"xВұа·қ"},{"u":"а¶әа·ҠвҖҚа¶»а·ӣ","f":"ffh%","i":"xВұа·ӣ"},{"u":"а¶әа·ҠвҖҚа¶»а·һ","f":"fh%!","i":"xВұа·һ"},{"u":"а¶әа·ҠвҖҚа¶»а¶Ӯ","f":"h%x","i":"xВұВ№"},{"u":"а¶әа·ҠвҖҚа¶»а¶ғ","f":"h%#","i":"xВұВә"},{"u":"а¶әа·ҠвҖҚа¶ә","f":"hH","i":"xВі"},{"u":"а¶әа·ҠвҖҚа¶»","f":"h%","i":"xВұ"},{"u":"а¶әа·Ҡ","f":"ha","i":"xЕ "},{"u":"а¶әа·Ҹ","f":"hd","i":"xВЈ"},{"u":"а¶әа·‘","f":"hE","i":"xВҰ"},{"u":"а¶әа·’","f":"hs","i":"xвҖ№"},{"u":"а¶әа·“","f":"hS","i":"xЕЎ"},{"u":"а¶әа·”","f":"hq","i":"xВ§"},{"u":"а¶әа·–","f":"hQ","i":"xВ«"},{"u":"а¶әа·ҳ","f":"hD","i":"xВҜ"},{"u":"а¶әа·І","f":"hDD","i":"xВҜВҜ"},{"u":"а¶әа·ҹ","f":"h!","i":"xВ°"},{"u":"а¶әа·і","f":"h!","i":"xа·і"},{"u":"а¶әа·ҷ","f":"fh","i":"В»x"},{"u":"а¶әа·ҡ","f":"fha","i":"В»xЕ "},{"u":"а¶әа·ӣ","f":"ffh","i":"xа·ӣ"},{"u":"а¶әа·ң","f":"fhd","i":"В»xВЈ"},{"u":"а¶әа·қ","f":"fhda","i":"В»xВЈЕ "},{"u":"а¶әа·һ","f":"fh!","i":"xа·һ"},{"u":"а¶әа¶Ӯ","f":"hx","i":"xВ№"},{"u":"а¶әа¶ғ","f":"h#","i":"xВә"},{"u":"а¶ә","f":"h","i":"x"},{"u":"а¶»а·ҠвҖҚа¶әа·Ҹ","f":"hвҖ“d","i":"yВіВЈ"},{"u":"а¶»а·ҠвҖҚа¶әа·ң","f":"hfвҖ“d","i":"yВіа·ң"},{"u":"а¶»а·ҠвҖҚа¶әа·қ","f":"hfвҖ“da","i":"yВіа·қ"},{"u":"а¶»а·ҠвҖҚа¶»а·Ҹ","f":"rвҖ“d","i":"yВұВЈ"},{"u":"а¶»а·ҠвҖҚа¶»а·җ","f":"rвҖ“e","i":"yВұВҘ"},{"u":"а¶»а·ҠвҖҚа¶»а·‘","f":"rвҖ“E","i":"yВұВҰ"},{"u":"а¶»а·ҠвҖҚа¶»а·’","f":"rвҖ“s","i":"yВұвҖ№"},{"u":"а¶»а·ҠвҖҚа¶»а·“","f":"rвҖ“S","i":"yВұЕЎ"},{"u":"а¶»а·ҠвҖҚа¶»а·ҷ","f":"rfвҖ“","i":"yВұВ»"},{"u":"а¶»а·ҠвҖҚа¶»а·ҡ","f":"rfвҖ“a","i":"yВұа·ҡ"},{"u":"а¶»а·ҠвҖҚа¶»а·ң","f":"rfвҖ“d","i":"yВұа·ң"},{"u":"а¶»а·ҠвҖҚа¶»а·қ","f":"rfвҖ“da","i":"yВұа·қ"},{"u":"а¶»а·ҠвҖҚа¶»а·ӣ","f":"rffвҖ“","i":"yВұа·ӣ"},{"u":"а¶»а·ҠвҖҚа¶»а·һ","f":"rfвҖ“!","i":"yВұа·һ"},{"u":"а¶»а·ҠвҖҚа¶»а¶Ӯ","f":"rвҖ“x","i":"yВұВ№"},{"u":"а¶»а·ҠвҖҚа¶»а¶ғ","f":"rвҖ“#","i":"yВұВә"},{"u":"а¶»а·ҠвҖҚа¶ә","f":"hвҖ“","i":"yВі"},{"u":"а¶»а·ҠвҖҚа¶»","f":"rвҖ“","i":"yВұ"},{"u":"а¶»а·Ҡ","f":"Вҫ","i":"M"},{"u":"а¶»а·Ҹ","f":"rd","i":"yВЈ"},{"u":"а¶»а·‘","f":"?","i":"Гё"},{"u":"а¶»а·’","f":"Гҹ","i":"Г№"},{"u":"а¶»а·“","f":"ГҚ","i":"Гә"},{"u":"а¶»а·”","f":"re","i":"yВҘ"},{"u":"а¶»а·–","f":"rE","i":"yВҰ"},{"u":"а¶»а·ҳ","f":"rD","i":"yВҜ"},{"u":"а¶»а·І","f":"rDD","i":"yВҜВҜ"},{"u":"а¶»а·ҹ","f":"r!","i":"yВ°"},{"u":"а¶»а·і","f":"r!","i":"yа·і"},{"u":"а¶»а·ҷ","f":"fr","i":"В»y"},{"u":"а¶»а·ҡ","f":"fra","i":"В»M"},{"u":"а¶»а·ӣ","f":"ffr","i":"yа·ӣ"},{"u":"а¶»а·ң","f":"frd","i":"В»yВЈ"},{"u":"а¶»а·қ","f":"frda","i":"В»yВЈЕ "},{"u":"а¶»а·һ","f":"fr!","i":"В»yВ°"},{"u":"а¶»а¶Ӯ","f":"rx","i":"yВ№"},{"u":"а¶»а¶ғ","f":"r#","i":"yВә"},{"u":"а¶»","f":"r","i":"y"},{"u":"а¶Ҫа·ҠвҖҚа¶әа·Ҹ","f":",Hd","i":"zВіВЈ"},{"u":"а¶Ҫа·ҠвҖҚа¶әа·ң","f":"f,Hd","i":"zВіа·ң"},{"u":"а¶Ҫа·ҠвҖҚа¶әа·қ","f":"f,Hda","i":"В»zВіВЈЕ "},{"u":"а¶Ҫа·ҠвҖҚа¶»а·Ҹ","f":",%d","i":"zВұВЈ"},{"u":"а¶Ҫа·ҠвҖҚа¶»а·җ","f":",%e","i":"zВұВҘ"},{"u":"а¶Ҫа·ҠвҖҚа¶»а·‘","f":",%E","i":"zВұВҰ"},{"u":"а¶Ҫа·ҠвҖҚа¶»а·’","f":",%s","i":"zВұвҖ№"},{"u":"а¶Ҫа·ҠвҖҚа¶»а·“","f":",%S","i":"zВұЕЎ"},{"u":"а¶Ҫа·ҠвҖҚа¶»а·ҷ","f":"f,%","i":"zВұВ»"},{"u":"а¶Ҫа·ҠвҖҚа¶»а·ҡ","f":"f,%a","i":"zВұа·ҡ"},{"u":"а¶Ҫа·ҠвҖҚа¶»а·ң","f":"f,%d","i":"zВұа·ң"},{"u":"а¶Ҫа·ҠвҖҚа¶»а·қ","f":"f,%da","i":"zВұа·қ"},{"u":"а¶Ҫа·ҠвҖҚа¶»а·ӣ","f":"ff,%","i":"zВұа·ӣ"},{"u":"а¶Ҫа·ҠвҖҚа¶»а·һ","f":"f,%!","i":"zВұа·һ"},{"u":"а¶Ҫа·ҠвҖҚа¶»а¶Ӯ","f":",%x","i":"zВұВ№"},{"u":"а¶Ҫа·ҠвҖҚа¶»а¶ғ","f":",%#","i":"zВұВә"},{"u":"а¶Ҫа·ҠвҖҚа¶ә","f":",H","i":"zВі"},{"u":"а¶Ҫа·ҠвҖҚа¶»","f":",%","i":"zВұ"},{"u":"а¶Ҫа·Ҡ","f":",a","i":"zЕ "},{"u":"а¶Ҫа·Ҹ","f":",d","i":"zВЈ"},{"u":"а¶Ҫа·‘","f":",E","i":"zВҰ"},{"u":"а¶Ҫа·’","f":",s","i":"zвҖ№"},{"u":"а¶Ҫа·“","f":",S","i":"zЕЎ"},{"u":"а¶Ҫа·”","f":"ВЁ","i":"Г»"},{"u":"а¶Ҫа·–","f":"ГҶ","i":"Гј"},{"u":"а¶Ҫа·ҳ","f":",D","i":"zВҜ"},{"u":"а¶Ҫа·І","f":",DD","i":"zВҜВҜ"},{"u":"а¶Ҫа·ҹ","f":",!","i":"zВ°"},{"u":"а¶Ҫа·і","f":",!","i":"zа·і"},{"u":"а¶Ҫа·ҷ","f":"f,","i":"В»z"},{"u":"а¶Ҫа·ҡ","f":"f,a","i":"В»zЕ "},{"u":"а¶Ҫа·ӣ","f":"ff,","i":"zа·ӣ"},{"u":"а¶Ҫа·ң","f":"f,d","i":"В»zВЈ"},{"u":"а¶Ҫа·қ","f":"f,da","i":"В»zВЈЕ "},{"u":"а¶Ҫа·һ","f":"f,!","i":"В»zВ°"},{"u":"а¶Ҫа¶Ӯ","f":",x","i":"zВ№"},{"u":"а¶Ҫа¶ғ","f":",#","i":"zВә"},{"u":"а¶Ҫ","f":",","i":"z"},{"u":"а·Җа·ҠвҖҚа¶әа·Ҹ","f":"jHd","i":"{ВіВЈ"},{"u":"а·Җа·ҠвҖҚа¶әа·ң","f":"fjHd","i":"В»{ВіВЈ"},{"u":"а·Җа·ҠвҖҚа¶әа·қ","f":"fjHda","i":"В»{ВіВЈЕ "},{"u":"а·Җа·ҠвҖҚа¶»а·Ҹ","f":"j%d","i":"{ВұВЈ"},{"u":"а·Җа·ҠвҖҚа¶»а·җ","f":"j%e","i":"{ВұВҘ"},{"u":"а·Җа·ҠвҖҚа¶»а·‘","f":"j%E","i":"{ВұВҰ"},{"u":"а·Җа·ҠвҖҚа¶»а·’","f":"Гә%","i":"{ВұвҖ№"},{"u":"а·Җа·ҠвҖҚа¶»а·“","f":"Г№%","i":"{ВұЕЎ"},{"u":"а·Җа·ҠвҖҚа¶»а·ҷ","f":"fj%","i":"{ВұВ»"},{"u":"а·Җа·ҠвҖҚа¶»а·ҡ","f":"fГө%","i":"{Вұа·ҡ"},{"u":"а·Җа·ҠвҖҚа¶»а·ң","f":"fj%d","i":"{Вұа·ң"},{"u":"а·Җа·ҠвҖҚа¶»а·қ","f":"fj%da","i":"{Вұа·қ"},{"u":"а·Җа·ҠвҖҚа¶»а·ӣ","f":"ffj%","i":"{Вұа·ӣ"},{"u":"а·Җа·ҠвҖҚа¶»а·һ","f":"fj%!","i":"{Вұа·һ"},{"u":"а·Җа·ҠвҖҚа¶»а¶Ӯ","f":"j%x","i":"{ВұВ№"},{"u":"а·Җа·ҠвҖҚа¶»а¶ғ","f":"j%#","i":"{ВұВә"},{"u":"а·Җа·ҠвҖҚа¶ә","f":"jH","i":"{Ві"},{"u":"а·Җа·ҠвҖҚа¶»","f":"j%","i":"{Вұ"},{"u":"а·Җа·Ҡ","f":"Гө","i":"N"},{"u":"а·Җа·Ҹ","f":"jd","i":"{ВЈ"},{"u":"а·Җа·‘","f":"jE","i":"{ВҰ"},{"u":"а·Җа·’","f":"Гә","i":"ГҪ"},{"u":"а·Җа·“","f":"Г№","i":"Гҫ"},{"u":"а·Җа·”","f":"jq","i":"{В§"},{"u":"а·Җа·–","f":"jQ","i":"{В«"},{"u":"а·Җа·ҳ","f":"jD","i":"{ВҜ"},{"u":"а·Җа·І","f":"jDD","i":"{ВҜВҜ"},{"u":"а·Җа·ҹ","f":"j!","i":"{В°"},{"u":"а·Җа·і","f":"j!","i":"{а·і"},{"u":"а·Җа·ҷ","f":"fj","i":"В»{"},{"u":"а·Җа·ҡ","f":"fГө","i":"В»N"},{"u":"а·Җа·ӣ","f":"ffj","i":"В»В»{"},{"u":"а·Җа·ң","f":"fjd","i":"В»{ВЈ"},{"u":"а·Җа·қ","f":"fjda","i":"В»{ВЈЕ "},{"u":"а·Җа·һ","f":"fj!","i":"{а·һ"},{"u":"а·Җа¶Ӯ","f":"jx","i":"{В№"},{"u":"а·Җа¶ғ","f":"j#","i":"{Вә"},{"u":"а·Җ","f":"j","i":"{"},{"u":"а·Ға·ҠвҖҚа¶әа·Ҹ","f":"YHd","i":"|ВіВЈ"},{"u":"а·Ға·ҠвҖҚа¶әа·ң","f":"fYHd","i":"В»|ВіВЈ"},{"u":"а·Ға·ҠвҖҚа¶әа·қ","f":"fYHda","i":"В»|ВіВЈЕ "},{"u":"а·Ға·ҠвҖҚа¶»а·Ҹ","f":"Y%d","i":"|ВұВЈ"},{"u":"а·Ға·ҠвҖҚа¶»а·җ","f":"Y%e","i":"|ВұВҘ"},{"u":"а·Ға·ҠвҖҚа¶»а·‘","f":"Y%E","i":"|ВұВҰ"},{"u":"а·Ға·ҠвҖҚа¶»а·’","f":"Y%s","i":"|ВұвҖ№"},{"u":"а·Ға·ҠвҖҚа¶»а·“","f":"вҖә","i":"|ВұЕЎ"},{"u":"а·Ға·ҠвҖҚа¶»а·ҷ","f":"fY%","i":"В»|Вұ"},{"u":"а·Ға·ҠвҖҚа¶»а·ҡ","f":"fY%a","i":"В»|Е Вұ"},{"u":"а·Ға·ҠвҖҚа¶»а·ң","f":"fY%d","i":"В»|ВұВЈ"},{"u":"а·Ға·ҠвҖҚа¶»а·қ","f":"fY%da","i":"В»|ВұВЈЕ "},{"u":"а·Ға·ҠвҖҚа¶»а·ӣ","f":"ffY%","i":"|Вұа·ӣ"},{"u":"а·Ға·ҠвҖҚа¶»а·һ","f":"fY%!","i":"|Вұа·һ"},{"u":"а·Ға·ҠвҖҚа¶»а¶Ӯ","f":"Y%x","i":"|ВұВ№"},{"u":"а·Ға·ҠвҖҚа¶»а¶ғ","f":"Y%#","i":"|ВұВә"},{"u":"а·Ға·ҠвҖҚа¶ә","f":"YH","i":"|Ві"},{"u":"а·Ға·ҠвҖҚа¶»","f":"Y%","i":"|Вұ"},{"u":"а·Ға·Ҡ","f":"Ya","i":"|Е "},{"u":"а·Ға·Ҹ","f":"Yd","i":"|ВЈ"},{"u":"а·Ға·‘","f":"YE","i":"|ВҰ"},{"u":"а·Ға·’","f":"Ys","i":"|вҖ№"},{"u":"а·Ға·“","f":"YS","i":"|ЕЎ"},{"u":"а·Ға·”","f":"Y=","i":"|В§"},{"u":"а·Ға·–","f":"Y+","i":"|В«"},{"u":"а·Ға·ҳ","f":"YD","i":"|ВҜ"},{"u":"а·Ға·І","f":"YDD","i":"|ВҜВҜ"},{"u":"а·Ға·ҹ","f":"Y!","i":"|В°"},{"u":"а·Ға·і","f":"Y!","i":"|а·і"},{"u":"а·Ға·ҷ","f":"fY","i":"В»|"},{"u":"а·Ға·ҡ","f":"fYa","i":"В»|Е "},{"u":"а·Ға·ӣ","f":"ffY","i":"В»В»|"},{"u":"а·Ға·ң","f":"fYd","i":"В»|ВЈ"},{"u":"а·Ға·қ","f":"fYda","i":"В»|ВЈЕ "},{"u":"а·Ға·һ","f":"fY!","i":"В»|В°"},{"u":"а·Ға¶Ӯ","f":"Yx","i":"|В№"},{"u":"а·Ға¶ғ","f":"Y#","i":"|Вә"},{"u":"а·Ғ","f":"Y","i":"|"},{"u":"а·Ӯа·ҠвҖҚа¶әа·Ҹ","f":"IHd","i":"}ВіВЈ"},{"u":"а·Ӯа·ҠвҖҚа¶әа·ң","f":"fIHd","i":"В»}ВіВЈ"},{"u":"а·Ӯа·ҠвҖҚа¶әа·қ","f":"fIHda","i":"В»}ВіВЈЕ "},{"u":"а·Ӯа·ҠвҖҚа¶»а·Ҹ","f":"I%d","i":"}ВұВЈ"},{"u":"а·Ӯа·ҠвҖҚа¶»а·җ","f":"I%e","i":"}ВұВҘ"},{"u":"а·Ӯа·ҠвҖҚа¶»а·‘","f":"I%E","i":"}ВұВҰ"},{"u":"а·Ӯа·ҠвҖҚа¶»а·’","f":"I%s","i":"}ВұвҖ№"},{"u":"а·Ӯа·ҠвҖҚа¶»а·“","f":"I%S","i":"}ВұЕЎ"},{"u":"а·Ӯа·ҠвҖҚа¶»а·ҷ","f":"fI%","i":"В»}Вұ"},{"u":"а·Ӯа·ҠвҖҚа¶»а·ҡ","f":"fI%a","i":"}Вұа·ҡ"},{"u":"а·Ӯа·ҠвҖҚа¶»а·ң","f":"fI%d","i":"}Вұа·ң"},{"u":"а·Ӯа·ҠвҖҚа¶»а·қ","f":"fI%da","i":"В»}ВұВЈЕ "},{"u":"а·Ӯа·ҠвҖҚа¶»а·ӣ","f":"ffI%","i":"}Вұа·ӣ"},{"u":"а·Ӯа·ҠвҖҚа¶»а·һ","f":"fI%!","i":"}Вұа·һ"},{"u":"а·Ӯа·ҠвҖҚа¶»а¶Ӯ","f":"I%x","i":"}ВұВ№"},{"u":"а·Ӯа·ҠвҖҚа¶»а¶ғ","f":"I%#","i":"}ВұВә"},{"u":"а·Ӯа·ҠвҖҚа¶ә","f":"IH","i":"}Ві"},{"u":"а·Ӯа·ҠвҖҚа¶»","f":"I%","i":"}Вұ"},{"u":"а·Ӯа·Ҡ","f":"Ia","i":"}Е "},{"u":"а·Ӯа·Ҹ","f":"Id","i":"}ВЈ"},{"u":"а·Ӯа·‘","f":"IE","i":"}ВҰ"},{"u":"а·Ӯа·’","f":"Is","i":"}вҖ№"},{"u":"а·Ӯа·“","f":"IS","i":"}ЕЎ"},{"u":"а·Ӯа·”","f":"Iq","i":"}В§"},{"u":"а·Ӯа·–","f":"IQ","i":"}В«"},{"u":"а·Ӯа·ҳ","f":"ID","i":"}ВҜ"},{"u":"а·Ӯа·І","f":"IDD","i":"}ВҜВҜ"},{"u":"а·Ӯа·ҹ","f":"I!","i":"}В°"},{"u":"а·Ӯа·і","f":"I!","i":"}а·і"},{"u":"а·Ӯа·ҷ","f":"fI","i":"В»}"},{"u":"а·Ӯа·ҡ","f":"fIa","i":"В»}Е "},{"u":"а·Ӯа·ӣ","f":"ffI","i":"}а·ӣ"},{"u":"а·Ӯа·ң","f":"fId","i":"В»}ВЈ"},{"u":"а·Ӯа·қ","f":"fIda","i":"В»}ВЈЕ "},{"u":"а·Ӯа·һ","f":"fI!","i":"В»}В°"},{"u":"а·Ӯа¶Ӯ","f":"Ix","i":"}В№"},{"u":"а·Ӯа¶ғ","f":"I#","i":"}Вә"},{"u":"а·Ӯ","f":"I","i":"}"},{"u":"а·ға·ҠвҖҚа¶әа·Ҹ","f":"iHd","i":"~ВіВЈ"},{"u":"а·ға·ҠвҖҚа¶әа·ң","f":"fiHd","i":"В»~ВіВЈ"},{"u":"а·ға·ҠвҖҚа¶әа·қ","f":"fiHda","i":"В»~ВіВЈЕ "},{"u":"а·ға·ҠвҖҚа¶»а·Ҹ","f":"i%d","i":"~ВұВЈ"},{"u":"а·ға·ҠвҖҚа¶»а·җ","f":"i%e","i":"~ВұВҘ"},{"u":"а·ға·ҠвҖҚа¶»а·‘","f":"i%E","i":"~ВұВҰ"},{"u":"а·ға·ҠвҖҚа¶»а·’","f":"i%s","i":"~ВұвҖ№"},{"u":"а·ға·ҠвҖҚа¶»а·“","f":"i%S","i":"~ВұЕЎ"},{"u":"а·ға·ҠвҖҚа¶»а·ҷ","f":"fi%","i":"В»~Вұ"},{"u":"а·ға·ҠвҖҚа¶»а·ҡ","f":"fi%a","i":"В»~Е Вұ"},{"u":"а·ға·ҠвҖҚа¶»а·ң","f":"fi%d","i":"В»~ВұВЈ"},{"u":"а·ға·ҠвҖҚа¶»а·қ","f":"fi%da","i":"В»~ВұВЈЕ "},{"u":"а·ға·ҠвҖҚа¶»а·ӣ","f":"ffi%","i":"~Вұа·ӣ"},{"u":"а·ға·ҠвҖҚа¶»а·һ","f":"fi%!","i":"~Вұа·һ"},{"u":"а·ға·ҠвҖҚа¶»а¶Ӯ","f":"i%x","i":"~ВұВ№"},{"u":"а·ға·ҠвҖҚа¶»а¶ғ","f":"i%#","i":"~ВұВә"},{"u":"а·ға·ҠвҖҚа¶ә","f":"iH","i":"~Ві"},{"u":"а·ға·ҠвҖҚа¶»","f":"i%","i":"~Вұ"},{"u":"а·ға·Ҡ","f":"ia","i":"~Е "},{"u":"а·ға·Ҹ","f":"id","i":"~ВЈ"},{"u":"а·ға·‘","f":"iE","i":"~ВҰ"},{"u":"а·ға·’","f":"is","i":"~вҖ№"},{"u":"а·ға·“","f":"iS","i":"~ЕЎ"},{"u":"а·ға·”","f":"iq","i":"~В§"},{"u":"а·ға·–","f":"iQ","i":"~В«"},{"u":"а·ға·ҳ","f":"iD","i":"~ВҜ"},{"u":"а·ға·І","f":"iDD","i":"~ВҜВҜ"},{"u":"а·ға·ҹ","f":"i!","i":"~В°"},{"u":"а·ға·і","f":"i!","i":"~а·і"},{"u":"а·ға·ҷ","f":"fi","i":"В»~"},{"u":"а·ға·ҡ","f":"fia","i":"В»~Е "},{"u":"а·ға·ӣ","f":"ffi","i":"~а·ӣ"},{"u":"а·ға·ң","f":"fid","i":"В»~ВЈ"},{"u":"а·ға·қ","f":"fida","i":"В»~ВЈЕ "},{"u":"а·ға·һ","f":"fi!","i":"В»~В°"},{"u":"а·ға¶Ӯ","f":"ix","i":"~В№"},{"u":"а·ға¶ғ","f":"i#","i":"~Вә"},{"u":"а·ғ","f":"i","i":"~"},{"u":"а·„а·ҠвҖҚа¶әа·Ҹ","f":"yHd","i":"Ж’ВіВЈ"},{"u":"а·„а·ҠвҖҚа¶әа·ң","f":"fyHd","i":"Ж’Віа·ң"},{"u":"а·„а·ҠвҖҚа¶әа·қ","f":"fyHda","i":"Ж’Віа·қ"},{"u":"а·„а·ҠвҖҚа¶»а·Ҹ","f":"y%d","i":"Ж’ВұВЈ"},{"u":"а·„а·ҠвҖҚа¶»а·җ","f":"y%e","i":"Ж’ВұВҘ"},{"u":"а·„а·ҠвҖҚа¶»а·‘","f":"y%E","i":"Ж’ВұВҰ"},{"u":"а·„а·ҠвҖҚа¶»а·’","f":"y%s","i":"Ж’ВұвҖ№"},{"u":"а·„а·ҠвҖҚа¶»а·“","f":"y%S","i":"Ж’ВұЕЎ"},{"u":"а·„а·ҠвҖҚа¶»а·ҷ","f":"fy%","i":"Ж’ВұВ»"},{"u":"а·„а·ҠвҖҚа¶»а·ҡ","f":"fy%a","i":"Ж’Вұа·ҡ"},{"u":"а·„а·ҠвҖҚа¶»а·ң","f":"fy%d","i":"Ж’Вұа·ң"},{"u":"а·„а·ҠвҖҚа¶»а·қ","f":"fy%da","i":"Ж’Вұа·қ"},{"u":"а·„а·ҠвҖҚа¶»а·ӣ","f":"ffy%","i":"Ж’Вұа·ӣ"},{"u":"а·„а·ҠвҖҚа¶»а·һ","f":"fy%!","i":"Ж’Вұа·һ"},{"u":"а·„а·ҠвҖҚа¶»а¶Ӯ","f":"y%x","i":"Ж’ВұВ№"},{"u":"а·„а·ҠвҖҚа¶»а¶ғ","f":"y%#","i":"Ж’ВұВә"},{"u":"а·„а·ҠвҖҚа¶ә","f":"yH","i":"Ж’Ві"},{"u":"а·„а·ҠвҖҚа¶»","f":"y%","i":"Ж’Вұ"},{"u":"а·„а·Ҡ","f":"ya","i":"Ж’Е "},{"u":"а·„а·Ҹ","f":"yd","i":"Ж’ВЈ"},{"u":"а·„а·‘","f":"yE","i":"Ж’ВҰ"},{"u":"а·„а·’","f":"ys","i":"Ж’вҖ№"},{"u":"а·„а·“","f":"yS","i":"Ж’ЕЎ"},{"u":"а·„а·”","f":"yq","i":"Ж’В§"},{"u":"а·„а·–","f":"yQ","i":"Ж’В«"},{"u":"а·„а·ҳ","f":"yD","i":"Ж’ВҜ"},{"u":"а·„а·І","f":"yDD","i":"Ж’ВҜВҜ"},{"u":"а·„а·ҹ","f":"y!","i":"Ж’В°"},{"u":"а·„а·і","f":"y!","i":"Ж’а·і"},{"u":"а·„а·ҷ","f":"fy","i":"В»Ж’"},{"u":"а·„а·ҡ","f":"fya","i":"В»Ж’Е "},{"u":"а·„а·ӣ","f":"ffy","i":"Ж’а·ӣ"},{"u":"а·„а·ң","f":"fyd","i":"В»Ж’ВЈ"},{"u":"а·„а·қ","f":"fyda","i":"В»Ж’ВЈЕ "},{"u":"а·„а·һ","f":"fy!","i":"Ж’а·һ"},{"u":"а·„а¶Ӯ","f":"yx","i":"Ж’В№"},{"u":"а·„а¶ғ","f":"y#","i":"Ж’Вә"},{"u":"а·„","f":"y","i":"Ж’"},{"u":"а·…а·ҠвҖҚа¶әа·Ҹ","f":"<Hd","i":"вҖҰВіВЈ"},{"u":"а·…а·ҠвҖҚа¶әа·ң","f":"f<Hd","i":"вҖҰВіа·ң"},{"u":"а·…а·ҠвҖҚа¶әа·қ","f":"f<Hda","i":"В»вҖҰВіВЈЕ "},{"u":"а·…а·ҠвҖҚа¶»а·Ҹ","f":"<%d","i":"вҖҰВұВЈ"},{"u":"а·…а·ҠвҖҚа¶»а·җ","f":"<%e","i":"вҖҰВұВҘ"},{"u":"а·…а·ҠвҖҚа¶»а·‘","f":"<%E","i":"вҖҰВұВҰ"},{"u":"а·…а·ҠвҖҚа¶»а·’","f":"<%s","i":"вҖҰВұвҖ№"},{"u":"а·…а·ҠвҖҚа¶»а·“","f":"<%S","i":"вҖҰВұЕЎ"},{"u":"а·…а·ҠвҖҚа¶»а·ҷ","f":"f<%","i":"вҖҰВұВ»"},{"u":"а·…а·ҠвҖҚа¶»а·ҡ","f":"f<%a","i":"вҖҰВұа·ҡ"},{"u":"а·…а·ҠвҖҚа¶»а·ң","f":"f<%d","i":"вҖҰВұа·ң"},{"u":"а·…а·ҠвҖҚа¶»а·қ","f":"f<%da","i":"вҖҰВұа·қ"},{"u":"а·…а·ҠвҖҚа¶»а·ӣ","f":"ff<%","i":"вҖҰВұа·ӣ"},{"u":"а·…а·ҠвҖҚа¶»а·һ","f":"f<%!","i":"вҖҰВұа·һ"},{"u":"а·…а·ҠвҖҚа¶»а¶Ӯ","f":"<%x","i":"вҖҰВұВ№"},{"u":"а·…а·ҠвҖҚа¶»а¶ғ","f":"<%#","i":"вҖҰВұВә"},{"u":"а·…а·ҠвҖҚа¶ә","f":"<H","i":"вҖҰВі"},{"u":"а·…а·ҠвҖҚа¶»","f":"<%","i":"вҖҰВұ"},{"u":"а·…а·Ҡ","f":"<a","i":"вҖҰЕ "},{"u":"а·…а·Ҹ","f":"<d","i":"вҖҰВЈ"},{"u":"а·…а·‘","f":"<E","i":"вҖҰВҰ"},{"u":"а·…а·’","f":"<s","i":"вҖҰвҖ№"},{"u":"а·…а·“","f":"<S","i":"вҖҰЕЎ"},{"u":"а·…а·”","f":"Вҝ","i":"вҖ "},{"u":"а·…а·–","f":"ВҝE","i":"вҖҰВ«"},{"u":"а·…а·ҳ","f":"<D","i":"вҖҰВҜ"},{"u":"а·…а·І","f":"<DD","i":"вҖҰВҜВҜ"},{"u":"а·…а·ҹ","f":"<!","i":"вҖҰВ°"},{"u":"а·…а·і","f":"<!","i":"вҖҰа·і"},{"u":"а·…а·ҷ","f":"f<","i":"В»вҖҰ"},{"u":"а·…а·ҡ","f":"f<a","i":"В»вҖҰЕ "},{"u":"а·…а·ӣ","f":"ff<","i":"вҖҰа·ӣ"},{"u":"а·…а·ң","f":"f<d","i":"В»вҖҰВЈ"},{"u":"а·…а·қ","f":"f<da","i":"В»вҖҰВЈЕ "},{"u":"а·…а·һ","f":"f<!","i":"вҖҰа·һ"},{"u":"а·…а¶Ӯ","f":"<x","i":"вҖҰВ№"},{"u":"а·…а¶ғ","f":"<#","i":"вҖҰВә"},{"u":"а·…","f":"<","i":"вҖҰ"},{"u":"а·Ҷа·ҠвҖҚа¶әа·Ҹ","f":"*Hd","i":"вҖЎВіВЈ"},{"u":"а·Ҷа·ҠвҖҚа¶әа·ң","f":"f*Hd","i":"В»вҖЎВіВЈ"},{"u":"а·Ҷа·ҠвҖҚа¶әа·қ","f":"f*Hda","i":"В»вҖЎВіВЈЕ "},{"u":"а·Ҷа·ҠвҖҚа¶»а·Ҹ","f":"*%d","i":"вҖЎВұВЈ"},{"u":"а·Ҷа·ҠвҖҚа¶»а·җ","f":"*%e","i":"вҖЎВұВҘ"},{"u":"а·Ҷа·ҠвҖҚа¶»а·‘","f":"*%E","i":"вҖЎВұВҰ"},{"u":"а·Ҷа·ҠвҖҚа¶»а·’","f":"*%s","i":"вҖЎВұвҖ№"},{"u":"а·Ҷа·ҠвҖҚа¶»а·“","f":"*%S","i":"вҖЎВұЕЎ"},{"u":"а·Ҷа·ҠвҖҚа¶»а·ҷ","f":"f*%","i":"В»вҖЎВұ"},{"u":"а·Ҷа·ҠвҖҚа¶»а·ҡ","f":"f*%a","i":"В»вҖЎЕ Вұ"},{"u":"а·Ҷа·ҠвҖҚа¶»а·ң","f":"f*%d","i":"В»вҖЎВұВЈ"},{"u":"а·Ҷа·ҠвҖҚа¶»а·қ","f":"f*%da","i":"В»вҖЎВұВЈЕ "},{"u":"а·Ҷа·ҠвҖҚа¶»а·ӣ","f":"ff*%","i":"вҖЎВұа·ӣ"},{"u":"а·Ҷа·ҠвҖҚа¶»а·һ","f":"f*%!","i":"вҖЎВұа·һ"},{"u":"а·Ҷа·ҠвҖҚа¶»а¶Ӯ","f":"*%x","i":"вҖЎВұВ№"},{"u":"а·Ҷа·ҠвҖҚа¶»а¶ғ","f":"*%#","i":"вҖЎВұВә"},{"u":"а·Ҷа·ҠвҖҚа¶ә","f":"*H","i":"вҖЎВі"},{"u":"а·Ҷа·ҠвҖҚа¶»","f":"*%","i":"вҖЎВұ"},{"u":"а·Ҷа·Ҡ","f":"*a","i":"вҖЎЕ "},{"u":"а·Ҷа·Ҹ","f":"*d","i":"вҖЎВЈ"},{"u":"а·Ҷа·‘","f":"*E","i":"вҖЎВҰ"},{"u":"а·Ҷа·’","f":"*s","i":"вҖЎвҖ№"},{"u":"а·Ҷа·“","f":"*S","i":"вҖЎЕЎ"},{"u":"а·Ҷа·”","f":"*q","i":"вҖЎВ§"},{"u":"а·Ҷа·–","f":"*Q","i":"вҖЎВ«"},{"u":"а·Ҷа·ҳ","f":"*D","i":"вҖЎВҜ"},{"u":"а·Ҷа·І","f":"*DD","i":"вҖЎВҜВҜ"},{"u":"а·Ҷа·ҹ","f":"*!","i":"вҖЎВ°"},{"u":"а·Ҷа·і","f":"*!","i":"вҖЎа·і"},{"u":"а·Ҷа·ҷ","f":"f*","i":"В»вҖЎ"},{"u":"а·Ҷа·ҡ","f":"f*a","i":"В»вҖЎ"},{"u":"а·Ҷа·ӣ","f":"ff*","i":"вҖЎа·ӣ"},{"u":"а·Ҷа·ң","f":"f*d","i":"В»вҖЎВЈ"},{"u":"а·Ҷа·қ","f":"f*da","i":"В»вҖЎВЈЕ "},{"u":"а·Ҷа·һ","f":"f*!","i":"В»вҖЎВ°"},{"u":"а·Ҷа¶Ӯ","f":"*x","i":"вҖЎВ№"},{"u":"а·Ҷа¶ғ","f":"*#","i":"вҖЎВә"},{"u":"а·Ҷ","f":"*","i":"вҖЎ"},{"u":"а¶Ҙа·ҠвҖҚа¶әа·Ҹ","f":"{Hd","i":"eВіВЈ"},{"u":"а¶Ҙа·ҠвҖҚа¶әа·ң","f":"f{Hd","i":"eВіа·ң"},{"u":"а¶Ҙа·ҠвҖҚа¶әа·қ","f":"f{Hda","i":"eВіа·қ"},{"u":"а¶Ҙа·ҠвҖҚа¶»а·Ҹ","f":"{%d","i":"eВұВЈ"},{"u":"а¶Ҙа·ҠвҖҚа¶»а·җ","f":"{%e","i":"eВұВҘ"},{"u":"а¶Ҙа·ҠвҖҚа¶»а·‘","f":"{%E","i":"eВұВҰ"},{"u":"а¶Ҙа·ҠвҖҚа¶»а·’","f":"{%s","i":"eВұвҖ№"},{"u":"а¶Ҙа·ҠвҖҚа¶»а·“","f":"{%S","i":"eВұЕЎ"},{"u":"а¶Ҙа·ҠвҖҚа¶»а·ҷ","f":"f{%","i":"eВұВ»"},{"u":"а¶Ҙа·ҠвҖҚа¶»а·ҡ","f":"f{%a","i":"eВұа·ҡ"},{"u":"а¶Ҙа·ҠвҖҚа¶»а·ң","f":"f{%d","i":"eВұа·ң"},{"u":"а¶Ҙа·ҠвҖҚа¶»а·қ","f":"f{%da","i":"eВұа·қ"},{"u":"а¶Ҙа·ҠвҖҚа¶»а·ӣ","f":"ff{%","i":"eВұа·ӣ"},{"u":"а¶Ҙа·ҠвҖҚа¶»а·һ","f":"f{%!","i":"eВұа·һ"},{"u":"а¶Ҙа·ҠвҖҚа¶»а¶Ӯ","f":"{%x","i":"eВұВ№"},{"u":"а¶Ҙа·ҠвҖҚа¶»а¶ғ","f":"{%#","i":"eВұВә"},{"u":"а¶Ҙа·ҠвҖҚа¶ә","f":"{H","i":"eВі"},{"u":"а¶Ҙа·ҠвҖҚа¶»","f":"{%","i":"eВұ"},{"u":"а¶Ҙа·Ҡ","f":"{a","i":"eЕ "},{"u":"а¶Ҙа·Ҹ","f":"{d","i":"eВЈ"},{"u":"а¶Ҙа·‘","f":"{E","i":"eВҰ"},{"u":"а¶Ҙа·’","f":"{s","i":"eвҖ№"},{"u":"а¶Ҙа·“","f":"{S","i":"eЕЎ"},{"u":"а¶Ҙа·”","f":"{q","i":"eВ§"},{"u":"а¶Ҙа·–","f":"{Q","i":"eВ«"},{"u":"а¶Ҙа·ҳ","f":"{D","i":"eВҜ"},{"u":"а¶Ҙа·І","f":"{DD","i":"eВҜВҜ"},{"u":"а¶Ҙа·ҹ","f":"{!","i":"eВ°"},{"u":"а¶Ҙа·і","f":"{!","i":"eа·і"},{"u":"а¶Ҙа·ҷ","f":"f{","i":"В»e"},{"u":"а¶Ҙа·ҡ","f":"f{a","i":"В»eЕ "},{"u":"а¶Ҙа·ӣ","f":"ff{","i":"eа·ӣ"},{"u":"а¶Ҙа·ң","f":"f{d","i":"В»Гҗ"},{"u":"а¶Ҙа·қ","f":"f{da","i":"В»ГҗЕ "},{"u":"а¶Ҙа·һ","f":"f{!","i":"eа·һ"},{"u":"а¶Ҙа¶Ӯ","f":"{x","i":"eВ№"},{"u":"а¶Ҙа¶ғ","f":"{#","i":"eВә"},{"u":"а¶Ҙ","f":"{","i":"e"},{"u":"а·ҠвҖҚа¶әа·Ҹ","f":"aвҖҚhd","i":"ВіВЈ"},{"u":"а·ҠвҖҚа¶әа·ң","f":"aвҖҚfhd","i":"Віа·ң"},{"u":"а·ҠвҖҚа¶әа·қ","f":"aвҖҚfhda","i":"Віа·қ"},{"u":"а·ҠвҖҚа¶»а·Ҹ","f":"%d","i":"ВұВЈ"},{"u":"а·ҠвҖҚа¶»а·җ","f":"%e","i":"ВұВҘ"},{"u":"а·ҠвҖҚа¶»а·‘","f":"%E","i":"ВұВҰ"},{"u":"а·ҠвҖҚа¶»а·’","f":"%s","i":"ВұвҖ№"},{"u":"а·ҠвҖҚа¶»а·“","f":"%S","i":"ВұЕЎ"},{"u":"а·ҠвҖҚа¶»а·ҷ","f":"aвҖҚfr","i":"ВұВ»"},{"u":"а·ҠвҖҚа¶»а·ҡ","f":"afВҫ","i":"Вұа·ҡ"},{"u":"а·ҠвҖҚа¶»а·ң","f":"aвҖҚfrd","i":"Вұа·ң"},{"u":"а·ҠвҖҚа¶»а·қ","f":"aвҖҚfrda","i":"Вұа·қ"},{"u":"а·ҠвҖҚа¶»а·ӣ","f":"aвҖҚffr","i":"Вұа·ӣ"},{"u":"а·ҠвҖҚа¶»а·һ","f":"aвҖҚfr!","i":"Вұа·һ"},{"u":"а·ҠвҖҚа¶»а¶Ӯ","f":"%x","i":"ВұВ№"},{"u":"а·ҠвҖҚа¶»а¶ғ","f":"%#","i":"ВұВә"},{"u":"а·ҠвҖҚа¶ә","f":"aвҖҚh","i":"Ві"},{"u":"а·ҠвҖҚа¶»","f":"%","i":"Вұ"},{"u":"а·Ҡ","f":"a","i":"Е "},{"u":"а·Ҹ","f":"d","i":"ВЈ"},{"u":"а·‘","f":"E","i":"ВҰ"},{"u":"а·’","f":"s","i":"вҖ№"},{"u":"а·“","f":"S","i":"ЕЎ"},{"u":"а·”","f":"q","i":"В§"},{"u":"а·–","f":"Q","i":"В«"},{"u":"а·ҳ","f":"D","i":"ВҜ"},{"u":"а·І","f":"DD","i":"ВҜВҜ"},{"u":"а·ҹ","f":"!","i":"В°"},{"u":"а·і","f":"!","i":"а·і"},{"u":"а·ҷ","f":"а·ҷ","i":"В»"},{"u":"а·ҡ","f":"а·ҡ","i":"а·ҡ"},{"u":"а·ӣ","f":"а·ӣ","i":"а·ӣ"},{"u":"а·ң","f":"а·ң","i":"а·ң"},{"u":"а·қ","f":"а·қ","i":"а·қ"},{"u":"а·һ","f":"а·һ","i":"а·һ"},{"u":"а¶Ӯ","f":"x","i":"В№"},{"u":"а¶ғ","f":"#","i":"Вә"},{"u":"а·җ","f":"e","i":"ВҘ"}]